Workbook

Sheet Nic
B1: Nic | D1: Aprile | E1: Maggio | F1: Giugno | G1: Luglio | H1: Agosto | I1: Settembre | J1: Ottobre | K1: Novembre | L1: Dicembre | M1: Gennaio | N1: Febbraio | O1: Marzo | P1: Aprile | Q1: Maggio | R1: Giugno | S1: Luglio | T1: Agosto | U1: Settembre | V1: Ottobre | W1: Novembre | X1: Dicembre | Y1: Gennaio | Z1: Febbraio | AA1: Marzo | AB1: Aprile | AC1: Maggio | AD1: Giugno | AE1: Luglio | AF1: Agosto | AG1: Settembre | AH1: Ottobre | AI1: Novembre | AJ1: Dicembre | AK1: Gennaio | AL1: Febbraio | AM1: Marzo | AN1: Aprile | AO1: Maggio | AP1: Giugno | AQ1: Luglio | AR1: Agosto | AS1: Settembre | AT1: Ottobre | AU1: Novembre | AV1: Dicembre | AW1: Gennaio | AX1: Febbraio | AY1: Marzo | AZ1: Aprile | BA1: Maggio | BB1: Giugno | BC1: Luglio | BD1: Agosto | BE1: Settembre | BF1: Ottobre | BG1: Novembre | BH1: Dicembre | BI1: Gennaio | BJ1: Febbraio | BK1: Marzo | BL1: Aprile | BM1: Maggio | BN1: Giugno | BO1: Luglio | BP1: Agosto | BQ1: Settembre | BR1: Ottobre | BS1: Novembre | BT1: Dicembre | BU1: Gennaio | BV1: Febbraio | BW1: Marzo | BX1: Aprile | BY1: Maggio | BZ1: Giugno | CA1: Luglio | CB1: Agosto | CC1: Settembre | CD1: Ottobre | CE1: Novembre | CF1: Dicembre | CG1: Gennaio | CH1: Febbraio | CI1: Marzo | CJ1: Aprile | CK1: Maggio | CL1: Giugno | CM1: Luglio | CN1: Agosto | CO1: Settembre | CP1: Ottobre | CQ1: Novembre | CR1: Dicembre
B2: Anno | D2: 1532 | E2: =D2+IF(E1="Gennaio",1,0) -> 1532 | F2: =E2+IF(F1="Gennaio",1,0) -> 1532 | G2: =F2+IF(G1="Gennaio",1,0) -> 1532 | H2: =G2+IF(H1="Gennaio",1,0) -> 1532 | I2: =H2+IF(I1="Gennaio",1,0) -> 1532 | J2: =I2+IF(J1="Gennaio",1,0) -> 1532 | K2: =J2+IF(K1="Gennaio",1,0) -> 1532 | L2: =K2+IF(L1="Gennaio",1,0) -> 1532 | ... CR2: =CQ2+IF(CR1="Gennaio",1,0) -> 1539
B3: Mese in-game | D3: =C3+1 -> 1 | E3: =D3+1 -> 2 | F3: =E3+1 -> 3 | G3: =F3+1 -> 4 | H3: =G3+1 -> 5 | I3: =H3+1 -> 6 | J3: =I3+1 -> 7 | K3: =J3+1 -> 8 | ... CR3: =CQ3+1 -> 93
E4: attrezzi sake | P4: drip cerimonia | V4: katane | Y4: casetta per associazione pescatori | AH4: barca grande | AK4: molo Takamura
A5: =MAX(D8:CC8) -> 1850 | B5: AV | E5: =ABS(E30) -> 150 | P5: =ABS(P45) -> 700 | V5: =ABS(V46) -> 2100 | Y5: =ABS(SUM(Y44:Y47)) -> 6850 | AH5: 6000 | AK5: =ABS(AK37) -> 2500 | AP5: 21 | BX5: =-(BX47+BX50+BX53) -> 46000
A6: =MIN(D8:CC8) -> -44150 | B6: NAV | D6: =SUM($C5:D5)+D7 -> 5180 | E6: =SUM($C5:E5)+E7 -> 5450 | F6: =SUM($C5:F5)+F7 -> 5720 | G6: =SUM($C5:G5)+G7 -> 5990 | H6: =SUM($C5:H5)+H7 -> 6260 | I6: =SUM($C5:I5)+I7 -> 6530 | J6: =SUM($C5:J5)+J7 -> 6800 | K6: =SUM($C5:K5)+K7 -> 7070 | ... AI6: =SUM($C5:AI5)+AI7 -> 18260 | AJ6: =SUM($C5:AI5)+AJ7 -> 18440 | AK6: =SUM($C5:AJ5)+AK7 -> 18060 | AL6: =SUM($C5:AK5)+AL7 -> 21680 | AM6: =SUM($C5:AL5)+AM7 -> 22800 | AN6: =SUM($C5:AM5)+AN7 -> 23920 | AO6: =SUM($C5:AN5)+AO7 -> 24950 | AP6: =SUM($C5:AO5)+AP7 -> 25959 | AQ6: =SUM($C5:AP5)+AQ7 -> 27030 | ... BV6: =SUM($C5:BU5)+BV7 -> 59580 | BW6: =SUM($C5:BW5)+BW7 -> 60630 | BX6: =SUM($C5:BX5)+BX7 -> 62480 | BY6: =SUM($C5:BY5)+BY7 -> 63230 | BZ6: =SUM($C5:BZ5)+BZ7 -> 60080 | CA6: =SUM($C5:CA5)+CA7 -> 61930 | CB6: =SUM($C5:CB5)+CB7 -> 63780 | CC6: =SUM($C5:CC5)+CC7 -> 64821
B7: Liquidi | C7: =SUM(C21:C1048576) -> 5000 | D7: =C7+SUM(D21:D57) -> 5180 | E7: =D7+SUM(E21:E57) -> 5300 | F7: =E7+SUM(F21:F57) -> 5570 | G7: =F7+SUM(G21:G57) -> 5840 | H7: =G7+SUM(H21:H57) -> 6110 | I7: =H7+SUM(I21:I57) -> 6380 | J7: =I7+SUM(J21:J57) -> 6650 | K7: =J7+SUM(K21:K57) -> 6920 | ... CC7: =CB7+SUM(CC21:CC57) -> 500
B8: Profitto netto | D8: =D7-C7 -> 180 | E8: =E7-D7 -> 120 | F8: =F7-E7 -> 270 | G8: =G7-F7 -> 270 | H8: =H7-G7 -> 270 | I8: =I7-H7 -> 270 | J8: =J7-I7 -> 270 | K8: =K7-J7 -> 270 | ... CC8: =CC7-CB7 -> 1041
A9: Terreni | B9: terreno edificabile a ovest [Kawa] | Y9: 50 | Z9: 50 | AA9: 50 | AB9: 50 | AC9: 50 | AD9: 50 | AE9: 50 | AF9: 50 | AG9: 50 | AH9: 50 | AI9: 50 | AJ9: 50 | AK9: 50 | AL9: 50 | AM9: 50 | AN9: 50 | AO9: 50 | AP9: 50 | AQ9: 50 | AR9: 50 | AS9: 50 | AT9: 50 | AU9: 50 | AV9: 50 | AW9: 50 | AX9: 50 | AY9: 50 | AZ9: 50 | BA9: 50 | BB9: 50 | BC9: 50 | BD9: 50 | BE9: 50 | BF9: 50 | BG9: 50 | BH9: 50 | BI9: 50 | BJ9: 50 | BK9: 50 | BL9: 50 | BM9: 50 | BN9: 50 | BO9: 50 | BP9: 50 | BQ9: 50 | BR9: 50 | BS9: 50 | BT9: 50 | BU9: 50 | BV9: 50 | BW9: 50 | BX9: 51 | BY9: 52 | BZ9: 53 | CA9: 54 | CB9: 55 | CC9: 56
A10: Altre tasse | B10: Tassa terreno edificabile | Y10: =-Y9*$A$60 -> -25 | Z10: =-Z9*$A$60 -> -25 | AA10: =-AA9*$A$60 -> -25 | AB10: =-AB9*$A$60 -> -25 | AC10: =-AC9*$A$60 -> -25 | AD10: =-AD9*$A$60 -> -25 | AE10: =-AE9*$A$60 -> -25 | AF10: =-AF9*$A$60 -> -25 | ... CC10: =-CC9*$A$60 -> -28
A11: Barche (unità) | B11: barca grande | AH11: 1 | AI11: 1 | AJ11: 1 | AK11: 1 | AL11: 1 | AM11: 1 | AN11: 1 | AO11: 1 | AP11: 1 | AQ11: 1 | AR11: 1 | AS11: 1 | AT11: 1 | AU11: 1 | AV11: 1 | AW11: 1 | AX11: 1 | AY11: 1 | AZ11: 1 | BA11: 1 | BB11: 1 | BC11: 1 | BD11: 1 | BE11: 1 | BF11: 1 | BG11: 1 | BH11: 1 | BI11: 1 | BJ11: 1 | BK11: 1 | BL11: 1 | BM11: 1 | BN11: 1 | BO11: 1 | BP11: 1 | BQ11: 1 | BR11: 1 | BS11: 1 | BT11: 1 | BU11: 1 | BV11: 1 | BW11: 1 | BX11: 1 | BY11: 1 | BZ11: 1 | CA11: 1 | CB11: 1 | CC11: 1
B12: barca media
B13: barca piccola | Y13: 4 | Z13: 4 | AA13: 4 | AB13: 4 | AC13: 4 | AD13: 4 | AE13: 4 | AF13: 4 | AG13: 4 | AH13: 4 | AI13: 4 | AJ13: 4 | AK13: 4 | AL13: 4 | AM13: 4 | AN13: 4 | AO13: 4 | AP13: 4 | AQ13: 4 | AR13: 4 | AS13: 4 | AT13: 4 | AU13: 4 | AV13: 4 | AW13: 4 | AX13: 4 | AY13: 4 | AZ13: 4 | BA13: 4 | BB13: 4 | BC13: 4 | BD13: 4 | BE13: 4 | BF13: 4 | BG13: 4 | BH13: 4 | BI13: 4 | BJ13: 4 | BK13: 4 | BL13: 4 | BM13: 4 | BN13: 4 | BO13: 4 | BP13: 4 | BQ13: 4 | BR13: 4 | BS13: 4 | BT13: 4 | BU13: 4 | BV13: 4 | BW13: 4 | BX13: 4 | BY13: 4 | BZ13: 4 | CA13: 4 | CB13: 4 | CC13: 4
A14: Associazione Pescatori | B14: Affitto barche | Y14: =Y11*$A$67+Y12*$A$68+Y13*$A$69 -> 100 | Z14: =Z11*$A$67+Z12*$A$68+Z13*$A$69 -> 100 | AA14: =AA11*$A$67+AA12*$A$68+AA13*$A$69 -> 100 | AB14: =AB11*$A$67+AB12*$A$68+AB13*$A$69 -> 100 | AC14: =AC11*$A$67+AC12*$A$68+AC13*$A$69 -> 100 | AD14: =AD11*$A$67+AD12*$A$68+AD13*$A$69 -> 100 | AE14: =AE11*$A$67+AE12*$A$68+AE13*$A$69 -> 100 | AF14: =AF11*$A$67+AF12*$A$68+AF13*$A$69 -> 100 | ... CC14: =CC11*$A$67+CC12*$A$68+CC13*$A$69 -> 250
B15: Offerte | Y15: 450 | Z15: =Y15-5 -> 445 | AA15: =Z15-5 -> 440 | AB15: =AA15-5 -> 435 | AC15: =AB15-5 -> 430 | AD15: =AC15-5 -> 425 | AE15: =AD15-5 -> 420 | AF15: =AE15-5 -> 415 | AG15: =AF15-5 -> 410 | ... CC15: =CB15-5 -> 170
B16: Assicurazione | Y16: =-(20*Y13+50*Y12+100*Y11) -> -80 | Z16: =-(20*Z13+50*Z12+100*Z11) -> -80 | AA16: =-(20*AA13+50*AA12+100*AA11) -> -80 | AB16: =-(20*AB13+50*AB12+100*AB11) -> -80 | AC16: =-(20*AC13+50*AC12+100*AC11) -> -80 | AD16: =-(20*AD13+50*AD12+100*AD11) -> -80 | AE16: =-(20*AE13+50*AE12+100*AE11) -> -80 | AF16: =-(20*AF13+50*AF12+100*AF11) -> -80 | ... CC16: =-(20*CC13+50*CC12+100*CC11) -> -180
AH17: prelievo Nic | AK17: prelievo Nic
B18: Spese e Movimenti | AH18: =-AH39 -> 0 | AK18: =-1000 -> -1000
B19: totale | X19: 0 | Y19: =X19+SUM(Y14:Y18) -> 470 | Z19: =Y19+SUM(Z14:Z18) -> 935 | AA19: =Z19+SUM(AA14:AA18) -> 1395 | AB19: =AA19+SUM(AB14:AB18) -> 1850 | AC19: =AB19+SUM(AC14:AC18) -> 2300 | AD19: =AC19+SUM(AD14:AD18) -> 2745 | AE19: =AD19+SUM(AE14:AE18) -> 3185 | AF19: =AE19+SUM(AF14:AF18) -> 3620 | ... CC19: =CB19+SUM(CC14:CC18) -> 20210
B21: Cibo | D21: 0 | E21: 0 | F21: 0 | G21: 0 | H21: 0 | I21: 0 | J21: 0 | K21: 0 | L21: 0 | M21: 0 | N21: 0 | O21: 0 | P21: 0 | Q21: 0 | R21: 0 | S21: 0 | T21: 0 | U21: 0 | V21: 0 | W21: 0 | X21: 0 | Y21: 0 | Z21: 0 | AA21: 0 | AB21: 0 | AC21: 0 | AD21: 0 | AE21: 0 | AF21: 0 | AG21: 0 | AH21: 0 | AI21: 0 | AJ21: 0 | AK21: 0 | AL21: 0 | AM21: 0 | AN21: 0 | AO21: 0 | AP21: 0 | AQ21: 0 | AR21: 0 | AS21: 0 | AT21: 0 | AU21: 0 | AV21: 0 | AW21: 0 | AX21: 0 | AY21: 0 | AZ21: 0 | BA21: 0 | BB21: 0 | BC21: 0 | BD21: 0 | BE21: 0 | BF21: 0 | BG21: 0 | BH21: 0 | BI21: 0 | BJ21: 0 | BK21: 0 | BL21: 0 | BM21: 0 | BN21: 0 | BO21: 0 | BP21: 0 | BQ21: 0 | BR21: 0 | BS21: 0 | BT21: 0 | BU21: 0 | BV21: 0 | BW21: 0 | BX21: 0 | BY21: 0 | BZ21: 0 | CA21: 0 | CB21: 0 | CC21: 0
B22: Affitto | D22: 0 | E22: 0 | F22: 0 | G22: 0 | H22: 0 | I22: 0 | J22: 0 | K22: 0 | L22: 0 | M22: 0 | N22: 0 | O22: 0 | P22: 0 | Q22: 0 | R22: 0 | S22: 0 | T22: 0 | U22: 0 | V22: 0 | W22: 0 | X22: 0 | Y22: 0 | Z22: 0 | AA22: 0 | AB22: 0 | AC22: 0 | AD22: 0 | AE22: 0 | AF22: 0 | AG22: 0 | AH22: 0 | AI22: 0 | AJ22: 0 | AK22: 0 | AL22: 0 | AM22: 0 | AN22: 0 | AO22: 0 | AP22: 0 | AQ22: 0 | AR22: 0 | AS22: 0 | AT22: 0 | AU22: 0 | AV22: 0 | AW22: 0 | AX22: 0 | AY22: 0 | AZ22: 0 | BA22: 0 | BB22: 0 | BC22: 0 | BD22: 0 | BE22: 0 | BF22: 0 | BG22: 0 | BH22: 0 | BI22: 0 | BJ22: 0 | BK22: 0 | BL22: 0 | BM22: 0 | BN22: 0 | BO22: 0 | BP22: 0 | BQ22: 0 | BR22: 0 | BS22: 0 | BT22: 0 | BU22: 0 | BV22: 0 | BW22: 0 | BX22: 0 | BY22: 0 | BZ22: 0 | CA22: 0 | CB22: 0 | CC22: 0
A23: Monaco (impiego)
B24: Salario da monaco + offerte | D24: =$A$61 -> 180 | E24: =$A$61 -> 180 | F24: =$A$61 -> 180 | G24: =$A$61 -> 180 | H24: =$A$61 -> 180 | I24: =$A$61 -> 180 | J24: =$A$61 -> 180 | K24: =$A$61 -> 180 | ... AP24: =$A$61 -> 180
B25: Studi monacali
B26: Funzionario locale | AQ26: 200 | AR26: 200 | AS26: 200 | AT26: 200 | AU26: 200 | AV26: 200 | AW26: 200 | AX26: 200 | AY26: 200 | AZ26: 200 | BA26: 200 | BB26: 200 | BC26: 200 | BD26: 200 | BE26: 200 | BF26: 200 | BG26: 200 | BH26: 200 | BI26: 200 | BJ26: 200 | BK26: 200 | BL26: 200 | BM26: 200 | BN26: 200 | BO26: 200 | BP26: 200 | BQ26: 200 | BR26: 200 | BS26: 200 | BT26: 200 | BU26: 200 | BV26: 200 | BW26: 200 | BX26: 1000 | BY26: 1000 | BZ26: 1000 | CA26: 1000 | CB26: 1000 | CC26: 1000
A27: Produzione di sake artigianale (business)
B28: Artigiano del sake | E28: =$A$62 -> 90 | F28: =$A$62 -> 90 | G28: =$A$62 -> 90 | H28: =$A$62 -> 90 | I28: =$A$62 -> 90 | J28: =$A$62 -> 90 | K28: =$A$62 -> 90 | L28: =$A$62 -> 90 | ... AG28: =$A$62 -> 90 | AK28: =$A$62 -> 90 | AL28: =$A$62 -> 90 | AM28: =$A$62 -> 90 | AN28: =$A$62 -> 90
B29: Vendita al tempio
B30: Attrezzi per il sake | E30: -150
B31: 🔒
A32: Impiegati Barca Grande
A33: 📜 | B33: Associazione
A34: 👤 | B34: Capitano | AK34: -1000 | AL34: -1000 | AM34: -1000 | AN34: -1000 | AO34: -1000 | AP34: -1000 | AQ34: -1000 | AR34: -1000 | AS34: -1000 | AT34: -1000 | AU34: -1000 | AV34: -1000 | AW34: -1000 | AX34: -1000 | AY34: -1000 | AZ34: -1000 | BA34: -1000 | BB34: -1000 | BC34: -1000 | BD34: -1000 | BE34: -1000 | BF34: -1000 | BG34: -1000 | BH34: -1000 | BI34: -1000 | BJ34: -1000 | BK34: -1000 | BL34: -1000 | BM34: -1000 | BN34: -1000 | BO34: -1000 | BP34: -1000 | BQ34: -1000 | BR34: -1000 | BS34: -1000 | BT34: -1000 | BU34: -1000 | BV34: -1000 | BW34: -1000 | BX34: -1000 | BY34: -1000 | BZ34: -1000 | CA34: -1000 | CB34: -1000 | CC34: -1000
A35: 👤 | B35: Nostromo (samurai) | AK35: -800 | AL35: -800 | AM35: -800 | AN35: -800 | AO35: -800 | AP35: -800 | AQ35: -800 | AR35: -800 | AS35: -800 | AT35: -800 | AU35: -800 | AV35: -800 | AW35: -800 | AX35: -800 | AY35: -800 | AZ35: -800 | BA35: -800 | BB35: -800 | BC35: -800 | BD35: -800 | BE35: -800 | BF35: -800 | BG35: -800 | BH35: -800 | BI35: -800 | BJ35: -800 | BK35: -800 | BL35: -800 | BM35: -800 | BN35: -800 | BO35: -800 | BP35: -800 | BQ35: -800 | BR35: -800 | BS35: -800 | BT35: -800 | BU35: -800 | BV35: -800 | BW35: -800 | BX35: -800 | BY35: -800 | BZ35: -800 | CA35: -800 | CB35: -800 | CC35: -800
A36: 👤 | B36: Navigatore | AK36: -700 | AL36: -700 | AM36: -700 | AN36: -700 | AO36: -700 | AP36: -700 | AQ36: -700 | AR36: -700 | AS36: -700 | AT36: -700 | AU36: -700 | AV36: -700 | AW36: -700 | AX36: -700 | AY36: -700 | AZ36: -700 | BA36: -700 | BB36: -700 | BC36: -700 | BD36: -700 | BE36: -700 | BF36: -700 | BG36: -700 | BH36: -700 | BI36: -700 | BJ36: -700 | BK36: -700 | BL36: -700 | BM36: -700 | BN36: -700 | BO36: -700 | BP36: -700 | BQ36: -700 | BR36: -700 | BS36: -700 | BT36: -700 | BU36: -700 | BV36: -700 | BW36: -700 | BX36: -700 | BY36: -700 | BZ36: -700 | CA36: -700 | CB36: -700 | CC36: -700
B37: Barca grande e molo (costi e introiti) | AG37: 1 barca grande | AH37: -6000 | AJ37: Molo | AK37: -2500
B38: Profitti vendite | AJ38: Pesca al largo (con volontari) | AK38: 2100 | AL38: 2100 | AM38: 2100 | AN38: 2100 | AO38: 2100 | AP38: 2100 | AQ38: 2100 | AR38: 2100 | AS38: 2100 | AT38: 2100 | AU38: 2100 | AV38: 2100 | AW38: 2100 | AX38: 2100 | AY38: 2100 | AZ38: 2100 | BA38: 2100 | BB38: 2100 | BC38: 2100 | BD38: 2100 | BE38: 2100 | BF38: 2100 | BG38: 2100 | BH38: 2100 | BI38: 2100 | BJ38: 2100 | BK38: 2100 | BL38: 2100 | BM38: 2100 | BN38: 2100 | BO38: 2100 | BP38: 2100 | BQ38: 2100 | BR38: 2100 | BS38: 2100 | BT38: 2100 | BU38: 2100 | BV38: 2100 | BW38: 2100 | BX38: 2100 | BY38: 2100 | BZ38: 2100 | CA38: 2100 | CB38: 2100 | CC38: 2100
B39: Movimenti | AJ39: Daimyoo supporto momentaneo | AK39: =ABS(SUM(AK34:AK36))*0.5 -> 1250 | AL39: =ABS(SUM(AL34:AL36))*0.5 -> 1250 | AM39: =ABS(SUM(AM34:AM36))*0.5 -> 1250 | AN39: =ABS(SUM(AN34:AN36))*0.5 -> 1250 | AO39: =ABS(SUM(AO34:AO36))*0.5 -> 1250 | AP39: =ABS(SUM(AP34:AP36))*0.5 -> 1250 | AQ39: =ABS(SUM(AQ34:AQ36))*0.5 -> 1250 | AR39: =ABS(SUM(AR34:AR36))*0.5 -> 1250 | ... CC39: =ABS(SUM(CC34:CC36))*0.5 -> 1250
A40: Hobbies
B41: Tiro con l'arco | U41: premio | V41: 50
A42: ⭐️ | B42: Spada
A44: {=SUM(COUNTIF(A23:A42, {"📜","👤"})) & "/11 Permessi"} -> 4/11 Permessi | C44: Bottino di partenza | P44: drip cerimonia | S44: boost produzione sake | X44: terreno | Y44: =-Y9*40 -> -2000 | AD44: torneo arco | AE44: 400 | AG44: prelievo associazione | AH44: 4000 | AJ44: prelievo associazione | AK44: =-AK18 -> 1000 | AO44: Quadro "Le Tre Figlie di Shirakumo" (dall'associazione) | AP44: -21
C45: 5000 | P45: -700 | S45: =400 -> 400 | V45: Katane Mayakashi | X45: 4 barche piccole | Y45: =-$A$66*Y13 -> -4000
V46: -2100 | X46: 1 casuccia | Y46: -650 | BY46: muro città | BZ46: -5000 | CB46: magazzino pubblico | CC46: 500
S47: torneo arco | X47: 1 piccolo shrine | Y47: -200 | BW47: baracche guardia civile | BX47: =-5000 * 3 -> -15000
S48: 50 | BX48: ass. pesca | BY48: -500
X49: bonifica bosco | Y49: -10 | BX49: pompa | BY49: -600
BW50: 1 scuola a Kanemura | BX50: -25000
BW53: campi per i poveri | BX53: -6000 | CB53: sistema di irrigazione | CC53: -1300
CB55: sake | CC55: -9
B59: Nota: il tempio si occupa dei permessi di vendita
A60: 0.5 | B60: tassa terreno edificabile $/kawa
A61: 180 | B61: range salario monaco
A62: 90 | B62: range sake
A64: 6000 | B64: costo barca grande
A65: 3000 | B65: costo barca media
A66: 1000 | B66: costo barca piccola
A67: =A68*2 -> 150 | B67: guadagno affitto barca grande
A68: =A69*3 -> 75 | B68: guadagno affitto barca media
A69: 25 | B69: guadagno affitto barca piccola

Sheet Cris
B1: Cris | D1: Aprile | E1: Maggio | F1: Giugno | G1: Luglio | H1: Agosto | I1: Settembre | J1: Ottobre | K1: Novembre | L1: Dicembre | M1: Gennaio | N1: Febbraio | O1: Marzo | P1: Aprile | Q1: Maggio | R1: Giugno | S1: Luglio | T1: Agosto | U1: Settembre | V1: Ottobre | W1: Novembre | X1: Dicembre | Y1: Gennaio | Z1: Febbraio | AA1: Marzo | AB1: Aprile | AC1: Maggio | AD1: Giugno | AE1: Luglio | AF1: Agosto | AG1: Settembre | AH1: Ottobre | AI1: Novembre | AJ1: Dicembre | AK1: Gennaio | AL1: Febbraio | AM1: Marzo | AN1: Aprile | AO1: Maggio | AP1: Giugno | AQ1: Luglio | AR1: Agosto | AS1: Settembre | AT1: Ottobre | AU1: Novembre | AV1: Dicembre | AW1: Gennaio | AX1: Febbraio | AY1: Marzo | AZ1: Aprile | BA1: Maggio | BB1: Giugno | BC1: Luglio | BD1: Agosto | BE1: Settembre | BF1: Ottobre | BG1: Novembre | BH1: Dicembre | BI1: Gennaio | BJ1: Febbraio | BK1: Marzo | BL1: Aprile | BM1: Maggio | BN1: Giugno | BO1: Luglio | BP1: Agosto | BQ1: Settembre | BR1: Ottobre | BS1: Novembre | BT1: Dicembre | BU1: Gennaio | BV1: Febbraio | BW1: Marzo | BX1: Aprile | BY1: Maggio | BZ1: Giugno | CA1: Luglio | CB1: Agosto | CC1: Settembre | CD1: Ottobre | CE1: Novembre | CF1: Dicembre | CG1: Gennaio | CH1: Febbraio | CI1: Marzo | CJ1: Aprile | CK1: Maggio | CL1: Giugno | CM1: Luglio | CN1: Agosto | CO1: Settembre | CP1: Ottobre | CQ1: Novembre | CR1: Dicembre
B2: Anno | D2: 1532 | E2: =D2+IF(E1="Gennaio",1,0) -> 1532 | F2: =E2+IF(F1="Gennaio",1,0) -> 1532 | G2: =F2+IF(G1="Gennaio",1,0) -> 1532 | H2: =G2+IF(H1="Gennaio",1,0) -> 1532 | I2: =H2+IF(I1="Gennaio",1,0) -> 1532 | J2: =I2+IF(J1="Gennaio",1,0) -> 1532 | K2: =J2+IF(K1="Gennaio",1,0) -> 1532 | L2: =K2+IF(L1="Gennaio",1,0) -> 1532 | ... CR2: =CQ2+IF(CR1="Gennaio",1,0) -> 1539
B3: Mese in-game | D3: =C3+1 -> 1 | E3: =D3+1 -> 2 | F3: =E3+1 -> 3 | G3: =F3+1 -> 4 | H3: =G3+1 -> 5 | I3: =H3+1 -> 6 | J3: =I3+1 -> 7 | K3: =J3+1 -> 8 | ... CR3: =CQ3+1 -> 93
A5: =MAX(D8:CC8) -> 4110 | B5: AV | C5: =ABS(C34) -> 700 | D5: =ABS(D23) -> 35 | E5: =ABS(E18+E19) -> 1020 | AB5: =ABS(AB33+AB34+AB31) -> 8350 | AE5: =-AE31 -> 500
A6: =MIN(D8:CC8) -> -7770 | B6: NAV | D6: =SUM($C5:D5)+D7 -> 4235 | E6: =SUM($C5:E5)+E7 -> 4514 | F6: =SUM($C5:F5)+F7 -> 4803 | G6: =SUM($C5:G5)+G7 -> 5156 | H6: =SUM($C5:H5)+H7 -> 5492 | I6: =SUM($C5:I5)+I7 -> 5833 | J6: =SUM($C5:J5)+J7 -> 6147 | K6: =SUM($C5:K5)+K7 -> 6465 | ... CC6: =SUM($C5:CC5)+CC7 -> 67088
B7: Liquidi | C7: =SUM(C11:C1048576) -> 4300 | D7: =C7+SUM(D11:D40) -> 3500 | E7: =D7+SUM(E11:E40) -> 2759 | F7: =E7+SUM(F11:F40) -> 3048 | G7: =F7+SUM(G11:G40) -> 3401 | H7: =G7+SUM(H11:H40) -> 3737 | I7: =H7+SUM(I11:I40) -> 4078 | J7: =I7+SUM(J11:J40) -> 4392 | K7: =J7+SUM(K11:K40) -> 4710 | ... CC7: =CB7+SUM(CC11:CC40) -> 56483
B8: Profitto netto | D8: =D7-C7 -> -800 | E8: =E7-D7 -> -741 | F8: =F7-E7 -> 289 | G8: =G7-F7 -> 353 | H8: =H7-G7 -> 336 | I8: =I7-H7 -> 341 | J8: =J7-I7 -> 314 | K8: =K7-J7 -> 318 | ... CC8: =CC7-CB7 -> 3483
A9: Terreni | B9: terreno edificabile a ovest [Kawa] | C9: 100 | D9: 100 | E9: =D9 -> 100 | F9: =E9 -> 100 | G9: =F9 -> 100 | H9: =G9 -> 100 | I9: =H9 -> 100 | J9: =I9 -> 100 | K9: =J9 -> 100 | L9: =K9 -> 100 | ... CC9: =CB9 -> 100
A10: Barche | B10: barca piccola | C10: 1 | D10: 1 | E10: 1 | F10: 1 | G10: 1 | H10: 1 | I10: 1 | J10: 1 | K10: 1 | L10: 1 | M10: 1 | N10: 1 | O10: 1 | P10: 1 | Q10: 1 | R10: 1 | S10: 1 | T10: 1 | U10: 1 | V10: 1 | W10: 1 | X10: 1 | Y10: 1 | Z10: 1 | AA10: 1 | AB10: 1 | AC10: 1 | AD10: 1 | AE10: 1 | AF10: 1 | AG10: 1 | AH10: 1 | AI10: 1 | AJ10: 1 | AK10: 1 | AL10: 1 | AM10: 1 | AN10: 1 | AO10: 1 | AP10: 1 | AQ10: 1 | AR10: 1 | AS10: 1 | AT10: 1 | AU10: 1 | AV10: 1 | AW10: 1 | AX10: 1 | AY10: 1 | AZ10: 1 | BA10: 1 | BB10: 1 | BC10: 1 | BD10: 1 | BE10: 1 | BF10: 1 | BG10: 1 | BH10: 1 | BI10: 1 | BJ10: 1 | BK10: 1 | BL10: 1 | BM10: 1 | BN10: 1 | BO10: 1 | BP10: 1 | BQ10: 1 | BR10: 1 | BS10: 1 | BT10: 1 | BU10: 1 | BV10: 1 | BW10: 1 | BX10: 1 | BY10: 1 | BZ10: 1 | CA10: 1 | CB10: 1 | CC10: 1
B11: Cibo | D11: -250 | E11: -250 | F11: -250 | G11: -250 | H11: -250 | I11: -250 | J11: -250 | K11: -250 | L11: -250 | M11: -250 | N11: -250 | O11: -250 | P11: -250 | Q11: -250 | R11: -250 | S11: -250 | T11: -250 | U11: -250 | V11: -250 | W11: -250 | X11: -250 | Y11: -250 | Z11: -250 | AA11: -250 | AB11: -250 | AC11: -250 | AD11: -250 | AE11: -250 | AF11: -250 | AG11: -250 | AH11: -250 | AI11: -250 | AJ11: -250 | AK11: -250 | AL11: -250 | AM11: -250 | AN11: -250 | AO11: -250 | AP11: -250 | AQ11: -250 | AR11: -250 | AS11: -250 | AT11: -250 | AU11: -250 | AV11: -250 | AW11: -250 | AX11: -250 | AY11: -250 | AZ11: -250 | BA11: -250 | BB11: -250 | BC11: -250 | BD11: -250 | BE11: -250 | BF11: -250 | BG11: -250 | BH11: -250 | BI11: -250 | BJ11: -250 | BK11: -250 | BL11: -250 | BM11: -250 | BN11: -250 | BO11: -250 | BP11: -250 | BQ11: -250 | BR11: -250 | BS11: -250 | BT11: -250 | BU11: -250 | BV11: -250 | BW11: -250 | BX11: -250 | BY11: -250 | BZ11: -250 | CA11: -250 | CB11: -250 | CC11: -250
B12: Affitto | D12: -50 | E12: -50
A13: Pescatore
B14: Pesca | E14: =$A$41 -> 425 | F14: =$A$41 -> 425 | G14: =$A$41 -> 425 | H14: =$A$41 -> 425 | I14: =$A$41 -> 425 | J14: =$A$41 -> 425 | K14: =$A$41 -> 425 | L14: =$A$41 -> 425 | M14: =$A$43 -> 575 | N14: =$A$43 -> 575 | O14: =$A$43 -> 575 | P14: =$A$43 -> 575 | Q14: =$A$43 -> 575 | R14: =$A$43 -> 575 | S14: =$A$43 -> 575 | T14: =$A$43 -> 575 | ... X14: =$A$43 -> 575
B15: Tassa porto | D15: =-$A$46 -> -20 | E15: =-$A$46 -> -20 | F15: =-$A$46 -> -20 | G15: =-$A$46 -> -20 | H15: =-$A$46 -> -20 | I15: =-$A$46 -> -20 | J15: =-$A$46 -> -20 | K15: =-$A$46 -> -20 | ... CC15: =-$A$46 -> -20
B16: Bancarella
A17: 📜 | B17: Tassa bancarella | D17: =-$A$47 -> -25 | E17: =-$A$47 -> -25 | F17: =-$A$47 -> -25 | G17: =-$A$47 -> -25 | H17: =-$A$47 -> -25 | I17: =-$A$47 -> -25 | J17: =-$A$47 -> -25 | K17: =-$A$47 -> -25 | ... X17: =-$A$47 -> -25
B18: 2 reti da pesca | E18: -20
A19: 📜 | B19: Barca da pesca | D19: barca | E19: -1000
A20: Taglialegna
B21: Taglialegna | E21: 249 | F21: 209 | G21: 243 | H21: 256 | I21: 261 | J21: 234 | K21: 238 | L21: 237
B22: Permesso tagliare legna | D22: 0 | E22: 0 | F22: 0 | G22: 0 | H22: 0 | I22: 0 | J22: 0 | K22: 0 | L22: 0
B23: ascia, machete | D23: -35
A24: Guardia
A25: ⭐️ | B25: guardia allevamento Granchi Kanemura | Y25: 900 | Z25: 900 | AA25: 900 | AB25: 900 | AC25: 900 | AD25: 900 | AE25: 1100 | AF25: 1100 | AG25: 1100 | AH25: 1100 | AI25: 1100 | AJ25: 1100 | AK25: 1100 | AL25: 1100 | AM25: 1100 | AN25: 1100 | AO25: 1100 | AP25: 1100 | AQ25: 1100 | AR25: 1100 | AS25: 1100 | AT25: 1100 | AU25: 1100 | AV25: 1100 | AW25: 1100 | AX25: 1100 | AY25: 1100 | AZ25: 1100 | BA25: 1100 | BB25: 1100 | BC25: 1100 | BD25: 1100 | BE25: 1100 | BF25: 1100 | BG25: 1100 | BH25: 1100 | BI25: 1300 | BJ25: 1300 | BK25: 1300 | BL25: 1300 | BM25: 1300 | BN25: 1300 | BO25: 1300 | BP25: 1300 | BQ25: 1300 | BR25: 1300 | BS25: 1300 | BT25: 1300 | BU25: 1300 | BV25: 1300 | BW25: 1300 | BX25: 1300 | BY25: 1300 | BZ25: 1300 | CA25: 1301 | CB25: 1302 | CC25: 1303
A26: Altre tasse | B26: Tassa terreno edificabile | E26: =-$A$45*E9 -> -50 | F26: =-$A$45*F9 -> -50 | G26: =-$A$45*G9 -> -50 | H26: =-$A$45*H9 -> -50 | I26: =-$A$45*I9 -> -50 | J26: =-$A$45*J9 -> -50 | K26: =-$A$45*K9 -> -50 | L26: =-$A$45*L9 -> -50 | ... CC26: =-$A$45*CC9 -> -50
A29: {=SUM(COUNTIF(A13:A25, {"📜","👤"})) & "/10 Permessi"} -> 2/10 Permessi | BU29: vende a Daichi | BV29: 300
C30: Bottino di partenza | AJ30: missione | AK30: 150
C31: 5000 | AA31: Casa a nord-est | AB31: =-6000-1500-500 -> -8000 | AD31: katana 931 | AE31: -500 | CB31: premio Daimyo | CC31: =10000/4 -> 2500
C33: 100 Kawa di terreno boschivo non-edificabile | D33: artigiano per costruire la casetta | G33: consegna casse | O33: samurai | X33: piccolo lingotto d'oro | AA33: Armatura da samurai | AB33: -300 | AD33: scatola del relitto | AE33: 300
C34: =-700 -> -700 | D34: -400 | G34: 30 | O34: 300 | X34: specchio da viaggio finemente decorato | AA34: 2 completi vestiti | AB34: -50 | AD34: piccolo lingotto | AE34: 3500
X35: Maschera da Cerimonia bianca finemente decorata
D36: bonifica bosco | O36: vende perle | AD36: mancia di netsuki | AE36: 30
D37: -20 | O37: =100 * 5 * 6 -> 3000
A41: 425 | B41: Pescatore (barca piccola)
A42: 500 | B42: Pescatore (barca media)
A43: 575 | B43: Pescatore (barca grande)
A44: 240 | B44: Taglialegna
A45: 0.5 | B45: tassa terreno edificabile $/kawa
A46: 20 | B46: Tassa porto
A47: 25 | B47: Tassa bancarella

Sheet Peter
B1: Peter | D1: Aprile | E1: Maggio | F1: Giugno | G1: Luglio | H1: Agosto | I1: Settembre | J1: Ottobre | K1: Novembre | L1: Dicembre | M1: Gennaio | N1: Febbraio | O1: Marzo | P1: Aprile | Q1: Maggio | R1: Giugno | S1: Luglio | T1: Agosto | U1: Settembre | V1: Ottobre | W1: Novembre | X1: Dicembre | Y1: Gennaio | Z1: Febbraio | AA1: Marzo | AB1: Aprile | AC1: Maggio | AD1: Giugno | AE1: Luglio | AF1: Agosto | AG1: Settembre | AH1: Ottobre | AI1: Novembre | AJ1: Dicembre | AK1: Gennaio | AL1: Febbraio | AM1: Marzo | AN1: Aprile | AO1: Maggio | AP1: Giugno | AQ1: Luglio | AR1: Agosto | AS1: Settembre | AT1: Ottobre | AU1: Novembre | AV1: Dicembre | AW1: Gennaio | AX1: Febbraio | AY1: Marzo | AZ1: Aprile | BA1: Maggio | BB1: Giugno | BC1: Luglio | BD1: Agosto | BE1: Settembre | BF1: Ottobre | BG1: Novembre | BH1: Dicembre | BI1: Gennaio | BJ1: Febbraio | BK1: Marzo | BL1: Aprile | BM1: Maggio | BN1: Giugno | BO1: Luglio | BP1: Agosto | BQ1: Settembre | BR1: Ottobre | BS1: Novembre | BT1: Dicembre | BU1: Gennaio | BV1: Febbraio | BW1: Marzo | BX1: Aprile | BY1: Maggio | BZ1: Giugno | CA1: Luglio | CB1: Agosto | CC1: Settembre | CD1: Ottobre | CE1: Novembre | CF1: Dicembre | CG1: Gennaio | CH1: Febbraio | CI1: Marzo | CJ1: Aprile | CK1: Maggio | CL1: Giugno | CM1: Luglio | CN1: Agosto | CO1: Settembre | CP1: Ottobre | CQ1: Novembre | CR1: Dicembre
B2: Anno | D2: 1532 | E2: =D2+IF(E1="Gennaio",1,0) -> 1532 | F2: =E2+IF(F1="Gennaio",1,0) -> 1532 | G2: =F2+IF(G1="Gennaio",1,0) -> 1532 | H2: =G2+IF(H1="Gennaio",1,0) -> 1532 | I2: =H2+IF(I1="Gennaio",1,0) -> 1532 | J2: =I2+IF(J1="Gennaio",1,0) -> 1532 | K2: =J2+IF(K1="Gennaio",1,0) -> 1532 | L2: =K2+IF(L1="Gennaio",1,0) -> 1532 | ... CR2: =CQ2+IF(CR1="Gennaio",1,0) -> 1539
B3: Mese in-game | D3: =C3+1 -> 1 | E3: =D3+1 -> 2 | F3: =E3+1 -> 3 | G3: =F3+1 -> 4 | H3: =G3+1 -> 5 | I3: =H3+1 -> 6 | J3: =I3+1 -> 7 | K3: =J3+1 -> 8 | ... CR3: =CQ3+1 -> 93
AH4: todo increase income | AN4: =SUMIF(AN11:AN39, ">=0") -> 4608
A5: =MAX(D8:CC8) -> 2224.76 | B5: AV | C5: =ABS(C51) -> 230 | D5: =ABS(D16+D51) -> 1400 | G5: =ABS(G20) -> 900 | J5: =ABS(J24) -> 900 | M5: =ABS(M32+M51) -> 5120 | Y5: =-Y28 -> 2700 | AG5: =ABS(SUM(Y53:AG53)) -> 27500 | AQ5: 100 | BX5: -5000 | BZ5: =12000+14000 -> 26000 | CA5: =ABS(CA50+CA53+CA57) -> 8206.66
A6: =MIN(D8:CC8) -> -24325.24 | B6: NAV | D6: =SUM($C5:D5)+D7 -> 5427 | E6: =SUM($C5:E5)+E7 -> 5914 | F6: =SUM($C5:F5)+F7 -> 6401 | G6: =SUM($C5:G5)+G7 -> 7133.2 | H6: =SUM($C5:H5)+H7 -> 7865.4 | I6: =SUM($C5:I5)+I7 -> 8597.6 | J6: =SUM($C5:J5)+J7 -> 9600 | K6: =SUM($C5:K5)+K7 -> 11602.4 | ... AA6: =SUM($C5:AA5)+AA7 -> 21042.533 | AB6: =SUM($C5:AA5)+AB7 -> 19823.858 | AC6: =SUM($C5:AC5)+AC7 -> 18705.182 | AD6: =SUM($C5:AD5)+AD7 -> 17586.507 | AE6: =SUM($C5:AD5)+AE7 -> 16079.311 | AF6: =SUM($C5:AF5)+AF7 -> 14272.116 | AG6: =SUM($C5:AG5)+AG7 -> 40131.32 | AH6: =SUM($C5:AH5)+AH7 -> 41321.08 | AI6: =SUM($C5:AI5)+AI7 -> 41925.84 | AJ6: =SUM($C5:AJ5)+AJ7 -> 42800.6 | AK6: =SUM($C5:AK5)+AK7 -> 43725.36 | AL6: =SUM($C5:AL5)+AL7 -> 44650.12 | AM6: =SUM($C5:AM5)+AM7 -> 45624.88 | ... CC6: =SUM($C5:CC5)+CC7 -> 84642.46
B7: Liquidi | C7: =SUM(C9:C1048576) -> 4770 | D7: =C7+SUM(D9:D1048576) -> 3797 | E7: =D7+SUM(E9:E1048576) -> 4284 | F7: =E7+SUM(F9:F1048576) -> 4771 | G7: =F7+SUM(G9:G1048576) -> 4603.2 | H7: =G7+SUM(H9:H1048576) -> 5335.4 | I7: =H7+SUM(I9:I1048576) -> 6067.6 | J7: =I7+SUM(J9:J1048576) -> 6170 | K7: =J7+SUM(K9:K1048576) -> 8172.4 | ... CC7: =CB7+SUM(CC9:CC1048576) -> 16585.8
B8: Profitto netto | D8: =D7-C7 -> -973 | E8: =E7-D7 -> 487 | F8: =F7-E7 -> 487 | G8: =G7-F7 -> -167.8 | H8: =H7-G7 -> 732.2 | I8: =I7-H7 -> 732.2 | J8: =J7-I7 -> 102.4 | K8: =K7-J7 -> 2002.4 | ... CC8: =CC7-CB7 -> 2204.56
B9: Cibo | D9: -270 | E9: -270 | F9: -270 | G9: -270 | H9: -270 | I9: -270 | J9: -270 | K9: -270 | L9: -270 | M9: -270 | N9: -270 | O9: -270 | P9: -270 | Q9: -270 | R9: -270 | S9: -270 | T9: -270 | U9: -270 | V9: -270 | W9: -270 | X9: -270 | Y9: -270 | Z9: -270 | AA9: -270 | AB9: -270 | AC9: -270 | AD9: -270 | AE9: -270 | AF9: -270 | AG9: -270 | AH9: -270 | AI9: -270 | AJ9: -270 | AK9: -270 | AL9: -270 | AM9: -270 | AN9: -270 | AO9: -270 | AP9: -270 | AQ9: -270 | AR9: -270 | AS9: -270 | AT9: -270 | AU9: -270 | AV9: -270 | AW9: -270 | AX9: -270 | AY9: -270 | AZ9: -270 | BA9: -270 | BB9: -270 | BC9: -270 | BD9: -270 | BE9: -270 | BF9: -270 | BG9: -270 | BH9: -270 | BI9: -270 | BJ9: -270 | BK9: -270 | BL9: -270 | BM9: -270 | BN9: -270 | BO9: -270 | BP9: -270 | BQ9: -270 | BR9: -270 | BS9: -270 | BT9: -270 | BU9: -270 | BV9: -270 | BW9: -270 | BX9: -270 | BY9: -270 | BZ9: -270 | CA9: -270 | CB9: -270 | CC9: -270
B10: Affitto | D10: -160 | E10: -160 | F10: -160 | G10: -160 | H10: -160 | I10: -160 | J10: -160 | K10: -160 | L10: -160 | M10: -160 | N10: -160 | O10: -160 | P10: -160 | Q10: -160 | R10: -160 | S10: -160 | T10: -160 | U10: -160 | V10: -160 | W10: -160 | X10: -160 | Y10: -160 | Z10: -160 | AA10: -160 | AB10: -160 | AC10: -160 | AD10: -160 | AE10: -160 | AF10: -160 | AG10: -160 | AH10: -160 | AI10: -160 | AJ10: -160 | AK10: -160 | AL10: -160 | AM10: -160 | AN10: -160 | AO10: -160 | AP10: -160 | AQ10: -160 | AR10: -160 | AS10: -160 | AT10: -160 | AU10: -160 | AV10: -160 | AW10: -160 | AX10: -160 | AY10: -160 | AZ10: -160 | BA10: -160 | BB10: -160 | BC10: -160 | BD10: -160 | BE10: -160 | BF10: -160 | BG10: -160 | BH10: -160 | BI10: -160 | BJ10: -160 | BK10: -160 | BL10: -160 | BM10: -160 | BN10: -160 | BO10: -160 | BP10: -160 | BQ10: -160 | BR10: -160 | BS10: -160 | BT10: -160 | BU10: -160 | BV10: -160 | BW10: -160 | BX10: -160 | BY10: -160 | BZ10: -160 | CA10: -160 | CB10: -160 | CC10: -160
A11: Tratta 1 (K-H-T) | B11: =SUM(D11:BZ16) -> 85980 | D11: =$A$59 -> 1100 | E11: =$A$59 -> 1100 | F11: =$A$59 -> 1100 | G11: =$A$59 -> 1100 | H11: =$A$59 -> 1100 | I11: =$A$59 -> 1100 | J11: =$A$59 -> 1100 | K11: =$A$59 -> 1100 | ... CC11: =$A$59 -> 1100
A12: 📜 | B12: Tassa rotta commerciale | D12: =-$A$66 -> -100 | E12: =-$A$66 -> -100 | F12: =-$A$66 -> -100 | G12: =-$A$66 -> -100 | H12: =-$A$66 -> -100 | I12: =-$A$66 -> -100 | J12: =-$A$66 -> -100 | K12: =-$A$66 -> -100 | ... CC12: =-$A$66 -> -100
A13: ⭐️ | B13: Burocrate
A14: 👤 | B14: Apprendista mercante | S14: =$A$59*$A$61 -> 660 | T14: =$A$59*$A$61 -> 660 | U14: =$A$59*$A$61 -> 660 | V14: =$A$59*$A$61 -> 660 | W14: =$A$59*$A$61 -> 660 | X14: =$A$59*$A$61 -> 660 | Y14: =$A$59*$A$61 -> 660 | Z14: =$A$59*$A$61 -> 660 | ... BH14: =$A$59*$A$61 -> 660 | BI14: =BH14 -> 660 | BJ14: =BI14 -> 660 | BK14: =BJ14 -> 660 | BL14: =BK14 -> 660 | BM14: =BL14 -> 660 | BN14: =BM14 -> 660 | BO14: =BN14 -> 660 | BP14: =BO14 -> 660 | ... BZ14: =BY14 -> 660
B15: salario | S15: =-$A$60 -> -270 | T15: =-$A$60 -> -270 | U15: =-$A$60 -> -270 | V15: =-$A$60 -> -270 | W15: =-$A$60 -> -270 | X15: =-$A$60 -> -270 | Y15: =-$A$60 -> -270 | Z15: =-$A$60 -> -270 | ... AD15: =-$A$60 -> -270 | AE15: -400 | AF15: -400 | AG15: -400 | AH15: -440 | AI15: -480 | AJ15: -520 | AK15: -520 | AL15: -520 | AM15: -520 | AN15: -520 | AO15: -520 | AP15: -520 | AQ15: -520 | AR15: -520 | AS15: -520 | AT15: -520 | AU15: -520 | AV15: -520 | AW15: -520 | AX15: -520 | AY15: -520 | AZ15: -520 | BA15: -520 | BB15: -520 | BC15: -520 | BD15: -520 | BE15: -520 | BF15: -520 | BG15: -520 | BH15: -520 | BI15: -520 | BJ15: -520 | BK15: -520 | BL15: -520 | BM15: -520 | BN15: -520 | BO15: =BN15 -> -520 | BP15: =BO15 -> -520 | BQ15: =BP15 -> -520 | BR15: =BQ15 -> -520 | BS15: =BR15 -> -520 | BT15: =BS15 -> -520 | BU15: =BT15 -> -520 | BV15: =BU15 -> -520 | ... BZ15: =BY15 -> -520
B16: Carro, cavallo, barili | D16: -900 | AN16: todo boost profitti Hirata
A17: Tratta 2 (U-H-K) | B17: =SUM(D17:BZ20) -> 8460 | G17: =$A$59*$A$61 -> 660 | H17: =$A$59*$A$61 -> 660 | I17: =$A$59*$A$61 -> 660 | J17: =$A$59*$A$61 -> 660 | K17: =$A$59*$A$61 -> 660 | L17: =$A$59*$A$61 -> 660 | M17: =$A$59*$A$61 -> 660 | N17: =$A$59*$A$61 -> 660 | ... BH17: =$A$59*$A$61 -> 660 | BI17: =BH17 -> 660 | BJ17: =BI17 -> 660 | BK17: =BJ17 -> 660 | BL17: =BK17 -> 660 | BM17: =BL17 -> 660 | BN17: =BM17 -> 660 | BO17: =BN17 -> 660 | BP17: =BO17 -> 660 | ... CC17: =CB17 -> 660
A18: 📜 | B18: Tassa rotta commerciale | G18: =- $A$66 -> -100 | H18: =- $A$66 -> -100 | I18: =- $A$66 -> -100 | J18: =- $A$66 -> -100 | K18: =- $A$66 -> -100 | L18: =- $A$66 -> -100 | M18: =- $A$66 -> -100 | N18: =- $A$66 -> -100 | ... CC18: =- $A$66 -> -100
A19: 👤 | B19: Apprendista mercante | G19: =-$A$60 -> -270 | H19: =-$A$60 -> -270 | I19: =-$A$60 -> -270 | J19: =-$A$60 -> -270 | K19: =-$A$60 -> -270 | L19: =-$A$60 -> -270 | M19: =-$A$60 -> -270 | N19: =-$A$60 -> -270 | ... AD19: =-$A$60 -> -270 | AE19: -400 | AF19: -400 | AG19: -400 | AH19: -440 | AI19: -480 | AJ19: -520 | AK19: -520 | AL19: -520 | AM19: -520 | AN19: -520 | AO19: -520 | AP19: -520 | AQ19: -520 | AR19: -520 | AS19: -520 | AT19: -520 | AU19: -520 | AV19: -520 | AW19: -520 | AX19: -520 | AY19: -520 | AZ19: -520 | BA19: -520 | BB19: -520 | BC19: -520 | BD19: -520 | BE19: -520 | BF19: -520 | BG19: -520 | BH19: -520 | BI19: -520 | BJ19: -520 | BK19: -520 | BL19: -520 | BM19: -520 | BN19: -520 | BO19: -520 | BP19: -520 | BQ19: -520 | BR19: -520 | BS19: -520 | BT19: -520 | BU19: -520 | BV19: =BU19 -> -520 | BW19: =BV19 -> -520 | BX19: =BW19 -> -520 | BY19: =BX19 -> -520 | BZ19: =BY19 -> -520 | CA19: =BZ19 -> -520 | CB19: =CA19 -> -520 | CC19: =CB19 -> -520
B20: Carro, cavallo, barili | G20: -900
A21: Tratta 3 (T-H-K) | B21: =SUM(D21:BZ24) -> 7590 | J21: =$A$59*$A$61 -> 660 | K21: =$A$59*$A$61 -> 660 | L21: =$A$59*$A$61 -> 660 | M21: =$A$59*$A$61 -> 660 | N21: =$A$59*$A$61 -> 660 | O21: =$A$59*$A$61 -> 660 | P21: =$A$59*$A$61 -> 660 | Q21: =$A$59*$A$61 -> 660 | ... BI21: =$A$59*$A$61 -> 660 | BJ21: =BI21 -> 660 | BK21: =BJ21 -> 660 | BL21: =BK21 -> 660 | BM21: =BL21 -> 660 | BN21: =BM21 -> 660 | BO21: =BN21 -> 660 | BP21: =BO21 -> 660 | BQ21: =BP21 -> 660 | ... CC21: =CB21 -> 660
A22: 📜 | B22: Tassa rotta commerciale | J22: =- $A$66 -> -100 | K22: =- $A$66 -> -100 | L22: =- $A$66 -> -100 | M22: =- $A$66 -> -100 | N22: =- $A$66 -> -100 | O22: =- $A$66 -> -100 | P22: =- $A$66 -> -100 | Q22: =- $A$66 -> -100 | ... CC22: =- $A$66 -> -100
A23: 👤 | B23: Apprendista mercante | J23: =-$A$60 -> -270 | K23: =-$A$60 -> -270 | L23: =-$A$60 -> -270 | M23: =-$A$60 -> -270 | N23: =-$A$60 -> -270 | O23: =-$A$60 -> -270 | P23: =-$A$60 -> -270 | Q23: =-$A$60 -> -270 | ... AD23: =-$A$60 -> -270 | AE23: -400 | AF23: -400 | AG23: -400 | AH23: -440 | AI23: -480 | AJ23: -520 | AK23: =AJ23 -> -520 | AL23: =AK23 -> -520 | AM23: =AL23 -> -520 | AN23: =AM23 -> -520 | AO23: =AN23 -> -520 | AP23: =AO23 -> -520 | AQ23: =AP23 -> -520 | AR23: =AQ23 -> -520 | ... CC23: =CB23 -> -520
B24: Carro, cavallo, barili | J24: -900
A25: Tratta 4 Marittima (T-H-K) | B25: =SUM(D25:BZ28) -> 11560 | Y25: =$A$67 -> 700 | Z25: =$A$67 -> 700 | AA25: =$A$67 -> 700 | AB25: =$A$67 -> 700 | AC25: =$A$67 -> 700 | AD25: =$A$67 -> 700 | AE25: =$A$67*1.1 -> 770 | AF25: =$A$67*1.1 -> 770 | AG25: 870 | AH25: =AG25 -> 870 | AI25: =AH25 -> 870 | AJ25: =AI25 -> 870 | AK25: =AJ25 -> 870 | AL25: =AK25 -> 870 | AM25: =AL25 -> 870 | AN25: =AM25 -> 870 | AO25: =AN25 -> 870 | ... CC25: =CB25 -> 870
A26: 📜 | B26: Tassa rotta commerciale (barca media) | Y26: =- $A$66 -> -100 | Z26: =- $A$66 -> -100 | AA26: =- $A$66 -> -100 | AB26: =- $A$66 -> -100 | AC26: =- $A$66 -> -100 | AD26: =- $A$66 -> -100 | AE26: =- $A$66 -> -100 | AF26: =- $A$66 -> -100 | ... CC26: =- $A$66 -> -100
A27: 👤 | B27: Apprendista mercante | Y27: =-$A$60 -> -270 | Z27: =-$A$60 -> -270 | AA27: =-$A$60 -> -270 | AB27: =-$A$60 -> -270 | AC27: =-$A$60 -> -270 | AD27: =-$A$60 -> -270 | AE27: -400 | AF27: -400 | AG27: -400 | AH27: -440 | AI27: -480 | AJ27: -520 | AK27: -520 | AL27: -520 | AM27: -520 | AN27: -520 | AO27: -520 | AP27: -520 | AQ27: -520 | AR27: -520 | AS27: -520 | AT27: -520 | AU27: -520 | AV27: -520 | AW27: -520 | AX27: -520 | AY27: -520 | AZ27: -520 | BA27: -520 | BB27: -520 | BC27: -520 | BD27: -520 | BE27: -520 | BF27: -520 | BG27: -520 | BH27: -520 | BI27: -520 | BJ27: -520 | BK27: -520 | BL27: -520 | BM27: -520 | BN27: -520 | BO27: -520 | BP27: -520 | BQ27: -520 | BR27: -520 | BS27: -520 | BT27: -520 | BU27: -520 | BV27: =BU27 -> -520 | BW27: =BV27 -> -520 | BX27: =BW27 -> -520 | BY27: =BX27 -> -520 | BZ27: =BY27 -> -520 | CA27: =BZ27 -> -520 | CB27: =CA27 -> -520 | CC27: =CB27 -> -520
B28: Barca e attrezzi | Y28: -2700
A29: Magazzino piccolo a Hakusui (rotte 1, 2, 3) | B29: =SUM(D29:BZ32) -> 7956
A30: 📜 | B30: Boost vendite | M30: =(M11+M17+M21)*$A$62 -> 484 | N30: =(N11+N17+N21)*$A$62 -> 484 | O30: =(O11+O17+O21)*$A$62 -> 484 | P30: =(P11+P17+P21)*$A$62 -> 484 | Q30: =(Q11+Q17+Q21)*$A$62 -> 484 | R30: =(R11+R17+R21)*$A$62 -> 484 | S30: =(S11+S17+S21)*$A$62 -> 484 | T30: =(T11+T17+T21)*$A$62 -> 484 | ... X30: =(X11+X17+X21)*$A$62 -> 484 | Y30: =(Y11+Y17+Y21+Y25)*$A$62 -> 624 | Z30: =(Z11+Z17+Z21+Z25)*$A$62 -> 624 | AA30: =(AA11+AA17+AA21+AA25)*$A$62 -> 624 | AB30: =(AB11+AB17+AB21+AB25)*$A$62 -> 624 | AC30: =(AC11+AC17+AC21+AC25)*$A$62 -> 624 | AD30: =(AD11+AD17+AD21+AD25)*$A$62 -> 624 | AE30: =(AE11+AE17+AE21+AE25)*$A$62 -> 638 | AF30: =(AF11+AF17+AF21+AF25)*$A$62 -> 638 | ... BZ30: =(BZ11+BZ17+BZ21+BZ25)*$A$62 -> 658 | CA30: =(CA11+CA17+CA21+CA25)*$A$72 -> 1316 | CB30: =(CB11+CB17+CB21+CB25)*$A$62 -> 658 | CC30: =(CC11+CC17+CC21+CC25)*$A$62 -> 658
A31: 👤 | B31: Mantenimento | M31: =-$A$64 -> -350 | N31: =-$A$64 -> -350 | O31: =-$A$64 -> -350 | P31: =-$A$64 -> -350 | Q31: =-$A$64 -> -350 | R31: =-$A$64 -> -350 | S31: =-$A$64 -> -350 | T31: =-$A$64 -> -350 | ... AD31: =-$A$64 -> -350 | AE31: -400 | AF31: -400 | AG31: -400 | AH31: -420 | AI31: -440 | AJ31: -460 | AK31: =AJ31 -> -460 | AL31: =AK31 -> -460 | AM31: =AL31 -> -460 | AN31: =AM31 -> -460 | AO31: =AN31 -> -460 | AP31: =AO31 -> -460 | AQ31: =AP31 -> -460 | AR31: =AQ31 -> -460 | ... CC31: =CB31 -> -460
B32: Prezzo magazzino | M32: =-A63 -> -5000
A33: Tasse bancarelle
A34: 📜 | B34: Tassa bancarella Kanemura | D34: =-$A$65 -> -25 | E34: =-$A$65 -> -25 | F34: =-$A$65 -> -25 | G34: =-$A$65 -> -25 | H34: =-$A$65 -> -25 | I34: =-$A$65 -> -25 | J34: =-$A$65 -> -25 | K34: =-$A$65 -> -25 | ... CC34: =-$A$65 -> -25
A35: 📜 | B35: Tassa bancarella Takamura | D35: =-$A$65 -> -25 | E35: =-$A$65 -> -25 | F35: =-$A$65 -> -25 | G35: =-$A$65 -> -25 | H35: =-$A$65 -> -25 | I35: =-$A$65 -> -25 | J35: =-$A$65 -> -25 | K35: =-$A$65 -> -25 | ... CC35: =-$A$65 -> -25
A36: 📜 | B36: Tassa bancarella Umihana | G36: =-$A$65 -> -25 | H36: =-$A$65 -> -25 | I36: =-$A$65 -> -25 | J36: =-$A$65 -> -25 | K36: =-$A$65 -> -25 | L36: =-$A$65 -> -25 | M36: =-$A$65 -> -25 | N36: =-$A$65 -> -25 | ... CC36: =-$A$65 -> -25
A37: ⭐️ | B37: Storia e Arte
A38: ⭐️ | B38: Modi di fare
A39: Assicurazione | D39: =-SUMIF(D11:D32, ">=0")*$A$69 -> -33 | E39: =-SUMIF(E11:E32, ">=0")*$A$69 -> -33 | F39: =-SUMIF(F11:F32, ">=0")*$A$69 -> -33 | G39: =-SUMIF(G11:G32, ">=0")*$A$69 -> -52.8 | H39: =-SUMIF(H11:H32, ">=0")*$A$69 -> -52.8 | I39: =-SUMIF(I11:I32, ">=0")*$A$69 -> -52.8 | J39: =-SUMIF(J11:J32, ">=0")*$A$69 -> -72.6 | K39: =-SUMIF(K11:K32, ">=0")*$A$69 -> -72.6 | ... CC39: =-SUMIF(CC11:CC32, ">=0")*$A$69 -> -118.44
BZ41: Burocrate | CA41: =1200 -> 1200 | CB41: =1200 -> 1200 | CC41: =1200 -> 1200
BZ43: 150
BZ44: 100 | CA44: 100 | CB44: 100 | CC44: 100
A47: {=SUM(COUNTIF(A11:A36, {"📜","👤"})) & "/13 Permessi"} -> 13/13 Permessi | C47: Bottino di partenza | L47: Riso Masanori | S47: Collana in oro con perle, regalata ai Nagatomo | V47: Tip per Masanori | AB47: consiglio legale relitto | AJ47: set da tè | AK47: -100 | BW47: spese disastro | BX47: -3800 | BZ47: materiale?
C48: 5000 | L48: -400 | S48: -500 | V48: -500 | X48: "security" | Y48: -830 | Z48: -830 | AA48: -830 | AB48: -100 | AD48: barca | AE48: 300 | AG48: rapina | AH48: 5 | AL48: Tempio Takamura | AM48: 50 | AN48: 50 | BZ48: set-back vendite?
AK49: Paga Takizawa | AL49: -100 | AM49: -100 | AN49: -100 | AP49: investimento sorella | AQ49: -5000 | BX49: 5000 | BZ49: danni ai campi | CA49: katana
C50: spada | D50: pergamena | J50: portafortuna | M50: vestito nero di seta, con tasche nascoste | P50: decide di vendere fagioli azuki in perdita | Y50: consulenza | AD50: Masanori | AE50: -200 | AF50: -200 | AG50: -150 | AH50: -200 | AI50: -200 | AJ50: -200 | AO50: todo tè Kleit | BX50: bonus | BZ50: vendita a doppio prezzo | CA50: -6.66
C51: -230 | D51: -500 | J51: -1000 | M51: -120 | P51: -100 | Y51: -200 | AP51: arco setup tiro con l'arco | AQ51: -100
BY52: casa Umihana | BZ52: =-12000*0.8 -> -9600 | CA52: arco buono
D53: ricerca info | J53: vendita portafortuna | K53: vendita portafortuna | M53: vende perle, spezie cinesi, e porcellana | X53: Casa a Hakusui | Y53: =-27500/9 -> -3055.5556 | Z53: =-27500/9 -> -3055.5556 | AA53: =-27500/9 -> -3055.5556 | AB53: =-27500/9 -> -3055.5556 | AC53: =-27500/9 -> -3055.5556 | AD53: =-27500/9 -> -3055.5556 | AE53: =-27500/9 -> -3055.5556 | AF53: =-27500/9 -> -3055.5556 | AG53: =-27500/9 -> -3055.5556 | AH53: cavallo | AI53: -300 | BY53: riparazioni casa | BZ53: -3000 | CA53: -1200
BY54: casa Takamura | BZ54: -11000
D55: -60 | J55: =1000 -> 1000 | K55: =1000 -> 1000 | M55: 300 | AH55: festa | AI55: -100 | BY55: riparazioni casa | BZ55: -2000
AI56: vendita tè | AJ56: 50 | CA56: upgrade magazzino
CA57: -7000
A59: 1100 | B59: range mercante
A60: 270 | B60: salario apprendista mercante
A61: 0.6 | B61: apprendista full-time multiplier
A62: 0.2 | B62: bonus magazzino piccolo
A63: 5000 | B63: prezzo magazzino piccolo
A64: 350 | B64: salario impiegato magazzino
A65: 25 | B65: Tassa bancarella
A66: 100 | B66: Tassa rotta commerciale
A67: 700 | B67: Rotta marittima
A69: 0.03 | B69: Tassa assicurazione mercanti
A72: 0.4 | B72: magazzino grande

Sheet Zilla
F1: Zilla | H1: Aprile | I1: Maggio | J1: Giugno | K1: Luglio | L1: Agosto | M1: Settembre | N1: Ottobre | O1: Novembre | P1: Dicembre | Q1: Gennaio | R1: Febbraio | S1: Marzo | T1: Aprile | U1: Maggio | V1: Giugno | W1: Luglio | X1: Agosto | Y1: Settembre | Z1: Ottobre | AA1: Novembre | AB1: Dicembre | AC1: Gennaio | AD1: Febbraio | AE1: Marzo | AF1: Aprile | AG1: Maggio | AH1: Giugno | AI1: Luglio | AJ1: Agosto | AK1: Settembre | AL1: Ottobre | AM1: Novembre | AN1: Dicembre | AO1: Gennaio | AP1: Febbraio | AQ1: Marzo | AR1: Aprile | AS1: Maggio | AT1: Giugno | AU1: Luglio | AV1: Agosto | AW1: Settembre | AX1: Ottobre | AY1: Novembre | AZ1: Dicembre | BA1: Gennaio | BB1: Febbraio | BC1: Marzo | BD1: Aprile | BE1: Maggio | BF1: Giugno | BG1: Luglio | BH1: Agosto | BI1: Settembre | BJ1: Ottobre | BK1: Novembre | BL1: Dicembre | BM1: Gennaio | BN1: Febbraio | BO1: Marzo | BP1: Aprile | BQ1: Maggio | BR1: Giugno | BS1: Luglio | BT1: Agosto | BU1: Settembre | BV1: Ottobre | BW1: Novembre | BX1: Dicembre | BY1: Gennaio | BZ1: Febbraio | CA1: Marzo | CB1: Aprile | CC1: Maggio | CD1: Giugno | CE1: Luglio | CF1: Agosto | CG1: Settembre | CH1: Ottobre | CI1: Novembre | CJ1: Dicembre | CK1: Gennaio | CL1: Febbraio | CM1: Marzo | CN1: Aprile | CO1: Maggio | CP1: Giugno | CQ1: Luglio | CR1: Agosto | CS1: Settembre | CT1: Ottobre | CU1: Novembre | CV1: Dicembre
F2: Anno | H2: 1532 | I2: =H2+IF(I1="Gennaio",1,0) -> 1532 | J2: =I2+IF(J1="Gennaio",1,0) -> 1532 | K2: =J2+IF(K1="Gennaio",1,0) -> 1532 | L2: =K2+IF(L1="Gennaio",1,0) -> 1532 | M2: =L2+IF(M1="Gennaio",1,0) -> 1532 | N2: =M2+IF(N1="Gennaio",1,0) -> 1532 | O2: =N2+IF(O1="Gennaio",1,0) -> 1532 | P2: =O2+IF(P1="Gennaio",1,0) -> 1532 | ... CV2: =CU2+IF(CV1="Gennaio",1,0) -> 1539
F3: Mese in-game | H3: =G3+1 -> 1 | I3: =H3+1 -> 2 | J3: =I3+1 -> 3 | K3: =J3+1 -> 4 | L3: =K3+1 -> 5 | M3: =L3+1 -> 6 | N3: =M3+1 -> 7 | O3: =N3+1 -> 8 | ... CV3: =CU3+1 -> 93
B5: =MAX(H9:CG9) -> 4270.2543 | F5: AV | G5: =ABS(G70) -> 75 | H5: =ABS(H22+H70) -> 1850 | K5: =ABS(K29) -> 900 | M5: =ABS(M67) -> 1000 | N5: =ABS(N36) -> 900 | Q5: =ABS(Q51+Q67) -> 320 | R5: =ABS(R67) -> 30 | V5: =ABS(V70) -> 500 | AE5: =-AE71 -> 130 | AF5: =-AF51-(6900+500)-AF67 -> 4900 | AL5: =ABS(AL67+AL68) -> 15500 | AT5: 20600 | AU5: 3000
B6: =MIN(H9:CG9) -> -27089.946 | F6: NAV | H6: =SUM($G5:H5)+H8 -> 5602 | I6: =SUM($G5:I5)+I8 -> 6204 | J6: =SUM($G5:J5)+J8 -> 6732.6667 | K6: =SUM($G5:K5)+K8 -> 7549.8667 | L6: =SUM($G5:L5)+L8 -> 8330.4 | M6: =SUM($G5:M5)+M8 -> 9147.6 | N6: =SUM($G5:N5)+N8 -> 10180 | O6: =SUM($G5:O5)+O8 -> 11212.4 | ... CG6: =SUM($G5:CG5)+CG8 -> 109297.53
F8: Liquidi | G8: =SUM(G12:G1048576) -> 4925 | H8: =G8+SUM(H12:H1048576) -> 3677 | I8: =H8+SUM(I12:I1048576) -> 4279 | J8: =I8+SUM(J12:J1048576) -> 4807.6667 | K8: =J8+SUM(K12:K1048576) -> 4724.8667 | L8: =K8+SUM(L12:L1048576) -> 5505.4 | M8: =L8+SUM(M12:M1048576) -> 5322.6 | N8: =M8+SUM(N12:N1048576) -> 5455 | O8: =N8+SUM(O12:O1048576) -> 6487.4 | ... CG8: =CF8+SUM(CG12:CG1048576) -> 59592.526
F9: Profitto netto | H9: =H8-G8 -> -1248 | I9: =I8-H8 -> 602 | J9: =J8-I8 -> 528.66667 | K9: =K8-J8 -> -82.8 | L9: =L8-K8 -> 780.53333 | M9: =M8-L8 -> -182.8 | N9: =N8-M8 -> 132.4 | O9: =O8-N8 -> 1032.4 | ... CG9: =CG8-CF8 -> 4270.2543
F12: Cibo | H12: -250 | I12: -250 | J12: -250 | K12: -250 | L12: -250 | M12: -250 | N12: -250 | O12: -250 | P12: -250 | Q12: -250 | R12: -250 | S12: -250 | T12: -250 | U12: -250 | V12: -250 | W12: -250 | X12: -250 | Y12: -250 | Z12: -250 | AA12: -250 | AB12: -250 | AC12: -250 | AD12: -250 | AE12: -250 | AF12: -250 | AG12: -250 | AH12: -250 | AI12: -250 | AJ12: -250 | AK12: -250 | AL12: -250 | AM12: -250 | AN12: -250 | AO12: -250 | AP12: -250 | AQ12: -250 | AR12: -250 | AS12: -250 | AT12: -250 | AU12: -250 | AV12: -250 | AW12: -250 | AX12: -250 | AY12: -250 | AZ12: -250 | BA12: -250 | BB12: -250 | BC12: -250 | BD12: -250 | BE12: -250 | BF12: -250 | BG12: -250 | BH12: -250 | BI12: -250 | BJ12: -250 | BK12: -250 | BL12: -250 | BM12: -250 | BN12: -250 | BO12: -250 | BP12: -250 | BQ12: -250 | BR12: -250 | BS12: -250 | BT12: -250 | BU12: -250 | BV12: -250 | BW12: -250 | BX12: -250 | BY12: -250 | BZ12: -250 | CA12: -250 | CB12: -250 | CC12: -250 | CD12: -250 | CE12: -250 | CF12: -250 | CG12: -250
F13: Affitto | H13: -90 | I13: -90 | J13: -90 | K13: -90 | L13: -90 | M13: -90 | N13: -90 | O13: -90 | P13: -90 | Q13: -90 | R13: -90 | S13: -90 | T13: -90 | U13: -90 | V13: -90 | W13: -90 | X13: -90 | Y13: -90 | Z13: -90 | AA13: -90 | AB13: -90 | AC13: -90 | AD13: -90 | AE13: -90 | AF13: -90 | AG13: -90 | AH13: -90 | AI13: -90 | AJ13: -90 | AK13: -90 | AL13: -90 | AM13: -90 | AN13: -90 | AO13: -90 | AP13: -90 | AQ13: -90 | AR13: -90 | AS13: -90 | AT13: -90 | AU13: -90 | AV13: -90 | AW13: -90 | AX13: -90 | AY13: -90 | AZ13: -90 | BA13: -90 | BB13: -90 | BC13: -90 | BD13: -90 | BE13: -90 | BF13: -90 | BG13: -90 | BH13: -90 | BI13: -90 | BJ13: -90 | BK13: -90 | BL13: -90 | BM13: -90 | BN13: -90 | BO13: -90 | BP13: -90 | BQ13: -90 | BR13: -90 | BS13: -90 | BT13: -90 | BU13: -90 | BV13: -90 | BW13: -90 | BX13: -90 | BY13: -90 | BZ13: -90 | CA13: -90 | CB13: -90 | CC13: -90 | CD13: -90 | CE13: -90 | CF13: -90 | CG13: -90
E14: =COUNTA(B15:C66) -> 13 | F14: / 13 Permessi
F16: Tratta 1 (U-H-T)
F17: Tratta 1 (T-H-U)
F18: Mercante (Zilla) | H18: =$E$75 -> 1100 | I18: =$E$75 -> 1100 | J18: =$E$75 -> 1100 | K18: =$E$75 -> 1100 | L18: =$E$75 -> 1100 | M18: =$E$75 -> 1100 | N18: =$E$75 -> 1100 | O18: =$E$75 -> 1100 | ... CG18: =$E$75 -> 1100
E19: ⭐️ | F19: Apprendista mercante | Z19: =$E$75*$E$77*$E$78 -> 528 | AA19: =$E$75*$E$77*$E$78 -> 528 | AB19: =$E$75*$E$77*$E$78 -> 528 | AC19: =$E$75*$E$77*$E$78 -> 528 | AD19: =$E$75*$E$77*$E$78 -> 528 | AE19: =$E$75*$E$77*$E$78 -> 528 | AF19: =$E$75*$E$77*$E$78 -> 528 | AG19: =$E$75*$E$77*$E$78 -> 528 | ... CG19: =$E$75*$E$77*$E$78 -> 528
F20: salario | Z20: =-$E$76 -> -300 | AA20: =-$E$76 -> -300 | AB20: =-$E$76 -> -300 | AC20: =-$E$76 -> -300 | AD20: =-$E$76 -> -300 | AE20: =-$E$76 -> -300 | AF20: =-$E$76 -> -300 | AG20: =-$E$76 -> -300 | AH20: =-$E$76 -> -300 | AI20: -400 | AJ20: -400 | AK20: -400 | AL20: -400 | AM20: -400 | AN20: -400 | AO20: -400 | AP20: -400 | AQ20: -400 | AR20: -400 | AS20: -400 | AT20: -400 | AU20: -400 | AV20: -400 | AW20: -400 | AX20: -400 | AY20: -400 | AZ20: -400 | BA20: -400 | BB20: -400 | BC20: -400 | BD20: -400 | BE20: =BD20 -> -400 | BF20: =BE20 -> -400 | BG20: =BF20 -> -400 | BH20: =BG20 -> -400 | BI20: =BH20 -> -400 | BJ20: =BI20 -> -400 | BK20: =BJ20 -> -400 | BL20: =BK20 -> -400 | ... CG20: =CF20 -> -400
B21: 📜 | F21: Tassa rotta commerciale | H21: =-$E$80 -> -100 | I21: =-$E$80 -> -100 | J21: =-$E$80 -> -100 | K21: =-$E$80 -> -100 | L21: =-$E$80 -> -100 | M21: =-$E$80 -> -100 | N21: =-$E$80 -> -100 | O21: =-$E$80 -> -100 | ... CG21: =-$E$80 -> -100
F22: Carro, cavallo, barili | H22: -900
F23: =SUM(H17:CG22) -> 85680
F25: Tratta 2 (U-H-T)
K26: =$E$75*$E$77 -> 660 | L26: =$E$75*$E$77 -> 660 | M26: =$E$75*$E$77 -> 660 | N26: =$E$75*$E$77 -> 660 | O26: =$E$75*$E$77 -> 660 | P26: =$E$75*$E$77 -> 660 | Q26: =$E$75*$E$77 -> 660 | R26: =$E$75*$E$77 -> 660 | ... CG26: =$E$75*$E$77 -> 660
B27: 👤 | F27: Apprendista mercante | K27: =-$E$76 -> -300 | L27: =-$E$76 -> -300 | M27: =-$E$76 -> -300 | N27: =-$E$76 -> -300 | O27: =-$E$76 -> -300 | P27: =-$E$76 -> -300 | Q27: =-$E$76 -> -300 | R27: =-$E$76 -> -300 | ... AH27: =-$E$76 -> -300 | AI27: -400 | AJ27: -400 | AK27: =AJ27 -> -400 | AL27: =AK27 -> -400 | AM27: =AL27 -> -400 | AN27: =AM27 -> -400 | AO27: =AN27 -> -400 | AP27: =AO27 -> -400 | AQ27: =AP27 -> -400 | AR27: =AQ27 -> -400 | ... CG27: =CF27 -> -400
B28: 📜 | F28: Tassa rotta commerciale | K28: =-$E$80 -> -100 | L28: =-$E$80 -> -100 | M28: =-$E$80 -> -100 | N28: =-$E$80 -> -100 | O28: =-$E$80 -> -100 | P28: =-$E$80 -> -100 | Q28: =-$E$80 -> -100 | R28: =-$E$80 -> -100 | ... CG28: =-$E$80 -> -100
F29: Carro, cavallo, barili | K29: -900
F30: =SUM(H25:CG29) -> 13500
F32: Tratta 3 (K-H-U)
N33: =$E$75*$E$77 -> 660 | O33: =$E$75*$E$77 -> 660 | P33: =$E$75*$E$77 -> 660 | Q33: =$E$75*$E$77 -> 660 | R33: =$E$75*$E$77 -> 660 | S33: =$E$75*$E$77 -> 660 | T33: =$E$75*$E$77 -> 660 | U33: =$E$75*$E$77 -> 660 | ... CG33: =$E$75*$E$77 -> 660
B34: 👤 | F34: Apprendista mercante | N34: =-$E$76 -> -300 | O34: =-$E$76 -> -300 | P34: =-$E$76 -> -300 | Q34: =-$E$76 -> -300 | R34: =-$E$76 -> -300 | S34: =-$E$76 -> -300 | T34: =-$E$76 -> -300 | U34: =-$E$76 -> -300 | ... AH34: =-$E$76 -> -300 | AI34: -400 | AJ34: -400 | AK34: -400 | AL34: =AK34 -> -400 | AM34: =AL34 -> -400 | AN34: =AM34 -> -400 | AO34: =AN34 -> -400 | AP34: =AO34 -> -400 | AQ34: =AP34 -> -400 | AR34: =AQ34 -> -400 | AS34: =AR34 -> -400 | ... CG34: =CF34 -> -400
B35: 📜 | F35: Tassa rotta commerciale | N35: =-$E$80 -> -100 | O35: =-$E$80 -> -100 | P35: =-$E$80 -> -100 | Q35: =-$E$80 -> -100 | R35: =-$E$80 -> -100 | S35: =-$E$80 -> -100 | T35: =-$E$80 -> -100 | U35: =-$E$80 -> -100 | ... CG35: =-$E$80 -> -100
F36: Carro, cavallo, barili | N36: -900
F37: =SUM(H32:CG36) -> 12720
F39: Tratta 4 (K-H-U)
B41: 👤 | F41: Apprendista mercante | AU41: =$E$75*$E$77 -> 660 | AV41: =$E$75*$E$77 -> 660 | AW41: =$E$75*$E$77 -> 660 | AX41: =$E$75*$E$77 -> 660 | AY41: =$E$75*$E$77 -> 660 | AZ41: =$E$75*$E$77 -> 660 | BA41: =$E$75*$E$77 -> 660 | BB41: =$E$75*$E$77 -> 660 | ... CG41: =$E$75*$E$77 -> 660
B42: 📜 | F42: Tassa rotta commerciale | AU42: -390 | AV42: =AU42 -> -390 | AW42: =AV42 -> -390 | AX42: =AW42 -> -390 | AY42: =AX42 -> -390 | AZ42: =AY42 -> -390 | BA42: =AZ42 -> -390 | BB42: =BA42 -> -390 | BC42: =BB42 -> -390 | ... CG42: =CF42 -> -390
F43: Carro, cavallo, barili | AU43: =-$E$80 -> -100 | AV43: =-$E$80 -> -100 | AW43: =-$E$80 -> -100 | AX43: =-$E$80 -> -100 | AY43: =-$E$80 -> -100 | AZ43: =-$E$80 -> -100 | BA43: =-$E$80 -> -100 | BB43: =-$E$80 -> -100 | ... CG43: =-$E$80 -> -100
F44: =SUM(H39:CG43) -> 6630 | AT44: barca media | AU44: -3000
F46: Magazzini (rotte 1, 2, 3)
F48: Boost vendite | Q48: =(Q18+Q26+Q33)*$E$81 -> 484 | R48: =(R18+R26+R33)*$E$81 -> 484 | S48: =(S18+S26+S33)*$E$81 -> 484 | T48: =(T18+T26+T33)*$E$81 -> 484 | U48: =(U18+U26+U33)*$E$81 -> 484 | V48: =(V18+V26+V33)*$E$81 -> 484 | W48: =(W18+W26+W33)*$E$81 -> 484 | X48: =(X18+X26+X33)*$E$81 -> 484 | Y48: =(Y18+Y26+Y33)*$E$81 -> 484 | Z48: =(Z18+Z26+Z33+Z19)*$E$81 -> 589.6 | AA48: =(AA18+AA26+AA33+AA19)*$E$81 -> 589.6 | AB48: =(AB18+AB26+AB33+AB19)*$E$81 -> 589.6 | AC48: =(AC18+AC26+AC33+AC19)*$E$81 -> 589.6 | AD48: =(AD18+AD26+AD33+AD19)*$E$81 -> 589.6 | AE48: =(AE18+AE26+AE33+AE19)*$E$81 -> 589.6 | AF48: =(AF18+AF26+AF33+AF19)*$E$82 -> 1474 | AG48: =(AG18+AG26+AG33+AG19)*$E$82 -> 1474 | AH48: =(AH18+AH26+AH33+AH19)*$E$82 -> 1474 | AI48: =(AI18+AI26+AI33+AI19)*$E$82 -> 1474 | AJ48: =(AJ18+AJ26+AJ33+AJ19)*$E$82 -> 1474 | AK48: =(AK18+AK26+AK33+AK19)*$E$82 -> 1474 | AL48: =(AL18+AL26+AL33+AL19)*$E$82 -> 1474 | AM48: =(AM18+AM26+AM33+AM19)*$E$82 -> 1474 | ... AT48: =(AT18+AT26+AT33+AT19)*$E$82 -> 1474 | AU48: =(AU18+AU26+AU33+AU19+AU41)*$E$82 -> 1804 | AV48: =(AV18+AV26+AV33+AV19)*$E$82 -> 1474 | AW48: =(AW18+AW26+AW33+AW19)*$E$82 -> 1474 | AX48: =(AX18+AX26+AX33+AX19)*$E$82 -> 1474 | AY48: =(AY18+AY26+AY33+AY19)*$E$82 -> 1474 | AZ48: =(AZ18+AZ26+AZ33+AZ19)*$E$82 -> 1474 | BA48: =(BA18+BA26+BA33+BA19)*$E$82 -> 1474 | BB48: =(BB18+BB26+BB33+BB19)*$E$82 -> 1474 | BC48: =(BC18+BC26+BC33+BC19)*$E$82 -> 1474 | ... CG48: =(CG18+CG26+CG33+CG19)*$E$82 -> 1474
B49: 👤 | C49: 👤 | F49: Mantenimento | Q49: =-$E$84 -> -350 | R49: =-$E$84 -> -350 | S49: =-$E$84 -> -350 | T49: =-$E$84 -> -350 | U49: =-$E$84 -> -350 | V49: =-$E$84 -> -350 | W49: =-$E$84 -> -350 | X49: =-$E$84 -> -350 | ... AE49: =-$E$84 -> -350 | AF49: =-$E$84*2 -> -700 | AG49: =-$E$84*2 -> -700 | AH49: =-$E$84*2 -> -700 | AI49: =-$E$84*2 -> -700 | AJ49: =-$E$84*2 -> -700 | AK49: =-$E$84*2 -> -700 | AL49: =-$E$84*2 -> -700 | AM49: =-$E$84*2 -> -700 | ... CG49: =-$E$84*2 -> -700
P50: magazzino piccolo (venduto) | Q50: era 69 gold
B51: 📜 | F51: magazzino grande Umihana | AE51: magazzino grande | AF51: -12000
F52: =SUM(H47:CG51) -> 32769.6
F54: Bancarelle
B55: 📜 | F55: Tassa bancarella Kanemura | H55: =-$E$79 -> -25 | I55: =-$E$79 -> -25 | J55: =-$E$79 -> -25 | K55: =-$E$79 -> -25 | L55: =-$E$79 -> -25 | M55: =-$E$79 -> -25 | N55: =-$E$79 -> -25 | O55: =-$E$79 -> -25 | ... CG55: =-$E$79 -> -25
B56: 📜 | F56: Tassa bancarella Takamura | K56: =-$E$79 -> -25 | L56: =-$E$79 -> -25 | M56: =-$E$79 -> -25 | N56: =-$E$79 -> -25 | O56: =-$E$79 -> -25 | P56: =-$E$79 -> -25 | Q56: =-$E$79 -> -25 | R56: =-$E$79 -> -25 | ... CG56: =-$E$79 -> -25
B57: 📜 | F57: Tassa bancarella Umihana | N57: =-$E$79 -> -25 | O57: =-$E$79 -> -25 | P57: =-$E$79 -> -25 | Q57: =-$E$79 -> -25 | R57: =-$E$79 -> -25 | S57: =-$E$79 -> -25 | T57: =-$E$79 -> -25 | U57: =-$E$79 -> -25 | ... CG57: =-$E$79 -> -25
F58: 🔒
E60: ⭐️ | F60: Pesca con l'arco | AC60: =1/7*500/2 -> 35.714286 | AD60: =1/7*500/2 -> 35.714286 | AE60: =1/7*500/2 -> 35.714286 | AF60: =1/7*500/2 -> 35.714286 | AG60: =1/7*500/2 -> 35.714286 | AH60: =1/7*500/2 -> 35.714286 | AI60: =1/7*500/2 -> 35.714286 | AJ60: =1/7*500/2 -> 35.714286 | ... CG60: =1/7*500/2 -> 35.714286
F61: Beneficenza tempio Takamura | AC61: -103 | AD61: -102 | AE61: -101 | AF61: -100 | AG61: -100 | AH61: -100 | AI61: -100 | AJ61: -100 | AK61: -100 | AL61: -100 | AM61: -100 | AN61: -100 | AO61: -100 | AP61: -100 | AQ61: -100 | AR61: -100 | AS61: -100 | AT61: -100 | AU61: -100 | AV61: -100 | AW61: -100 | AX61: -100 | AY61: -100 | AZ61: -100 | BA61: -100 | BB61: -100 | BC61: -100 | BD61: -100 | BE61: -100 | BF61: -100 | BG61: -100 | BH61: -100 | BI61: -100 | BJ61: -100 | BK61: -100 | BL61: -100 | BM61: -100 | BN61: -100 | BO61: -100 | BP61: -100 | BQ61: -100 | BR61: -100 | BS61: -100 | BT61: -100 | BU61: -100 | BV61: -100 | BW61: -100 | BX61: -99 | BY61: -98 | BZ61: -97 | CA61: -96 | CB61: -95 | CC61: -94 | CD61: -93 | CE61: -92 | CF61: -91 | CG61: -90
F64: Assicurazione | H64: =-SUMIF(H17:H58, ">=0")*$E$88 -> -33 | I64: =-SUMIF(I17:I58, ">=0")*$E$88 -> -33 | J64: =-SUMIF(J17:J58, ">=0")*$E$88 -> -33 | K64: =-SUMIF(K17:K58, ">=0")*$E$88 -> -52.8 | L64: =-SUMIF(L17:L58, ">=0")*$E$88 -> -52.8 | M64: =-SUMIF(M17:M58, ">=0")*$E$88 -> -52.8 | N64: =-SUMIF(N17:N58, ">=0")*$E$88 -> -72.6 | O64: =-SUMIF(O17:O58, ">=0")*$E$88 -> -72.6 | ... CG64: =-SUMIF(CG17:CG58, ">=0")*$E$88 -> -152.46
G66: Bottino di partenza | M66: Katane Mayakashi 205, 208 | Q66: Monete Cinesi d'oro | R66: tè con marchio e sigillo imperiale cinese | AE66: Kimono per Saori | AF66: -700 | CF66: premio Daimyo | CG66: =10000/4 -> 2500
G67: 5000 | M67: -1000 | Q67: -320 | R67: -30 | AE67: Kimono per se stesso (3+1) | AF67: -300 | AK67: katana | AL67: -2000 | AS67: Casa Umihana | AT67: -20600 | CA67: danni tsunami | CB67: -9000
AE68: vendita magazzino piccolo Umihana | AF68: =(69+5)*0.9*100 -> 6660 | AK68: katana | AL68: -13500 | AS68: Permesso mercantile | AT68: -8100
G69: spada | H69: Katana Mayakashi 163 | J69: ricerca in biblioteca | L69: giro in montagna | Q69: vendita spezie cinesi | R69: scatolina di legno di olii profumati | V69: pavimenti magazzino
G70: -75 | H70: -950 | J70: =-J18*2/30 -> -73.333333 | L70: =-L18/30 -> -36.666667 | Q70: 100 | R70: -50 | V70: -500
AD71: arco | AE71: -130
E75: 1100 | F75: range profitti
E76: 300 | F76: salario dipendente
E77: 0.6 | F77: apprendista multiplier
E78: 0.8 | F78: multiplier tratta busy
E79: 25 | F79: tassa bancarella
E80: 100 | F80: Tassa rotta commerciale
E81: 0.2 | F81: bonus magazzino piccolo
E82: 0.5 | F82: bonus magazzino grande
E83: 6900 | F83: Costo magazzino
E84: 350 | F84: salario impiegato magazzino
E85: 25 | F85: Tassa bancarella
E86: 100 | F86: Tassa rotta commerciale
E88: 0.03 | F88: Assicurazione mensile mercanti

Sheet Vito
D1: Vito | F1: Aprile | G1: Maggio | H1: Giugno | I1: Luglio | J1: Agosto | K1: Settembre | L1: Ottobre | M1: Novembre | N1: Dicembre | O1: Gennaio | P1: Febbraio | Q1: Marzo | R1: Aprile | S1: Maggio | T1: Giugno | U1: Luglio | V1: Agosto | W1: Settembre | X1: Ottobre | Y1: Novembre | Z1: Dicembre | AA1: Gennaio | AB1: Febbraio | AC1: Marzo | AD1: Aprile | AE1: Maggio | AF1: Giugno | AG1: Luglio | AH1: Agosto | AI1: Settembre | AJ1: Ottobre | AK1: Novembre | AL1: Dicembre | AM1: Gennaio | AN1: Febbraio | AO1: Marzo | AP1: Aprile | AQ1: Maggio | AR1: Giugno | AS1: Luglio | AT1: Agosto | AU1: Settembre | AV1: Ottobre | AW1: Novembre | AX1: Dicembre | AY1: Gennaio | AZ1: Febbraio | BA1: Marzo | BB1: Aprile | BC1: Maggio | BD1: Giugno | BE1: Luglio | BF1: Agosto | BG1: Settembre | BH1: Ottobre | BI1: Novembre | BJ1: Dicembre | BK1: Gennaio | BL1: Febbraio | BM1: Marzo | BN1: Aprile | BO1: Maggio | BP1: Giugno | BQ1: Luglio | BR1: Agosto | BS1: Settembre | BT1: Ottobre | BU1: Novembre | BV1: Dicembre | BW1: Gennaio | BX1: Febbraio | BY1: Marzo | BZ1: Aprile | CA1: Maggio | CB1: Giugno | CC1: Luglio | CD1: Agosto | CE1: Settembre | CF1: Ottobre | CG1: Novembre | CH1: Dicembre | CI1: Gennaio | CJ1: Febbraio | CK1: Marzo | CL1: Aprile | CM1: Maggio | CN1: Giugno | CO1: Luglio | CP1: Agosto | CQ1: Settembre | CR1: Ottobre | CS1: Novembre | CT1: Dicembre
D2: Anno | F2: 1532 | G2: =F2+IF(G1="Gennaio",1,0) -> 1532 | H2: =G2+IF(H1="Gennaio",1,0) -> 1532 | I2: =H2+IF(I1="Gennaio",1,0) -> 1532 | J2: =I2+IF(J1="Gennaio",1,0) -> 1532 | K2: =J2+IF(K1="Gennaio",1,0) -> 1532 | L2: =K2+IF(L1="Gennaio",1,0) -> 1532 | M2: =L2+IF(M1="Gennaio",1,0) -> 1532 | N2: =M2+IF(N1="Gennaio",1,0) -> 1532 | ... CT2: =CS2+IF(CT1="Gennaio",1,0) -> 1539
D3: Mese in-game | F3: =E3+1 -> 1 | G3: =F3+1 -> 2 | H3: =G3+1 -> 3 | I3: =H3+1 -> 4 | J3: =I3+1 -> 5 | K3: =J3+1 -> 6 | L3: =K3+1 -> 7 | M3: =L3+1 -> 8 | ... CT3: =CS3+1 -> 93
AM4: prestito | AY4: prestito
C5: =MAX(F9:CE9) -> 4920 | D5: AV | O5: =ABS(O35) -> 350 | U5: =ABS(U34+U37) -> 800 | AM5: -5000 | AR5: =20 -> 20 | AY5: 5000
C6: =MIN(F9:CE9) -> -3990 | D6: NAV | F6: =SUM($E5:F5)+F8 -> 5223 | G6: =SUM($E5:G5)+G8 -> 5479 | H6: =SUM($E5:H5)+H8 -> 5774 | I6: =SUM($E5:I5)+I8 -> 6024 | J6: =SUM($E5:J5)+J8 -> 6304 | K6: =SUM($E5:K5)+K8 -> 6584 | L6: =SUM($E5:L5)+L8 -> 6864 | M6: =SUM($E5:M5)+M8 -> 7144 | ... CE6: =SUM($E5:CE5)+CE8 -> 60066
D8: Liquidi | E8: =SUM(E11:E1048576) -> 5000 | F8: =E8+SUM(F11:F1048576) -> 5223 | G8: =F8+SUM(G11:G1048576) -> 5479 | H8: =G8+SUM(H11:H1048576) -> 5774 | I8: =H8+SUM(I11:I1048576) -> 6024 | J8: =I8+SUM(J11:J1048576) -> 6304 | K8: =J8+SUM(K11:K1048576) -> 6584 | L8: =K8+SUM(L11:L1048576) -> 6864 | M8: =L8+SUM(M11:M1048576) -> 7144 | ... CE8: =CD8+SUM(CE11:CE1048576) -> 58896
D9: Profitto netto | F9: =F8-E8 -> 223 | G9: =G8-F8 -> 256 | H9: =H8-G8 -> 295 | I9: =I8-H8 -> 250 | J9: =J8-I8 -> 280 | K9: =K8-J8 -> 280 | L9: =L8-K8 -> 280 | M9: =M8-L8 -> 280 | ... CE9: =CE8-CD8 -> 4060
D12: Cibo | F12: 0 | G12: 0 | H12: 0 | I12: 0 | J12: 0 | K12: 0 | L12: 0 | M12: 0 | N12: 0 | O12: 0 | P12: 0 | Q12: 0 | R12: 0 | S12: 0 | T12: 0 | U12: 0 | V12: 0 | W12: 0 | X12: 0 | Y12: 0 | Z12: 0 | AA12: 0 | AB12: 0 | AC12: 0 | AD12: 0 | AE12: 0 | AF12: 0 | AG12: 0 | AH12: 0 | AI12: 0 | AJ12: 0 | AK12: 0 | AL12: 0 | AM12: 0 | AN12: 0 | AO12: 0 | AP12: 0 | AQ12: 0 | AR12: 0 | AS12: 0 | AT12: 0 | AU12: 0 | AV12: 0 | AW12: 0 | AX12: 0 | AY12: 0 | AZ12: 0 | BA12: 0 | BB12: 0 | BC12: 0 | BD12: 0 | BE12: 0 | BF12: 0 | BG12: 0 | BH12: 0 | BI12: 0 | BJ12: 0 | BK12: 0 | BL12: 0 | BM12: 0 | BN12: 0 | BO12: 0 | BP12: 0 | BQ12: 0 | BR12: 0 | BS12: 0 | BT12: 0 | BU12: 0 | BV12: 0 | BW12: 0 | BX12: 0 | BY12: 0 | BZ12: 0 | CA12: 0 | CB12: 0 | CC12: 0 | CD12: 0 | CE12: 0
D13: Affitto | F13: 0 | G13: 0 | H13: 0 | I13: 0 | J13: 0 | K13: 0 | L13: 0 | M13: 0 | N13: 0 | O13: 0 | P13: 0 | Q13: 0 | R13: 0 | S13: 0 | T13: 0 | U13: 0 | V13: 0 | W13: 0 | X13: 0 | Y13: 0 | Z13: 0 | AA13: 0 | AB13: 0 | AC13: 0 | AD13: 0 | AE13: 0 | AF13: 0 | AG13: 0 | AH13: 0 | AI13: 0 | AJ13: 0 | AK13: 0 | AL13: 0 | AM13: 0 | AN13: 0 | AO13: 0 | AP13: 0 | AQ13: 0 | AR13: 0 | AS13: 0 | AT13: 0 | AU13: 0 | AV13: 0 | AW13: 0 | AX13: 0 | AY13: 0 | AZ13: 0 | BA13: 0 | BB13: 0 | BC13: 0 | BD13: 0 | BE13: 0 | BF13: 0 | BG13: 0 | BH13: 0 | BI13: 0 | BJ13: 0 | BK13: 0 | BL13: 0 | BM13: 0 | BN13: 0 | BO13: 0 | BP13: 0 | BQ13: 0 | BR13: 0 | BS13: 0 | BT13: 0 | BU13: 0 | BV13: 0 | BW13: 0 | BX13: 0 | BY13: 0 | BZ13: 0 | CA13: 0 | CB13: 0 | CC13: 0 | CD13: 0 | CE13: 0
C14: =COUNTA(A15:B42) -> 4 | D14: Permessi
D16: Impiego
D17: Assistente
C18: ⭐️ | D18: Salario | I18: =$C$42 -> 280 | J18: =$C$42 -> 280 | K18: =$C$42 -> 280 | L18: =$C$42 -> 280 | M18: =$C$42 -> 280 | N18: =$C$42 -> 280 | O18: =$C$42 -> 280 | P18: =$C$42 -> 280 | ... CE18: =$C$42 -> 280
D21: Servizio Postale a Cavallo | AJ21: aiuto zilla | AO21: +3 | AU21: +2 | BZ21: 2
D22: vendite | AD22: 200 | AE22: =AD22 -> 200 | AF22: =AE22 -> 200 | AG22: =AF22 -> 200 | AH22: =AG22 -> 200 | AI22: =AH22 -> 200 | AJ22: 400 | AK22: =AJ22 -> 400 | AL22: =AK22 -> 400 | AM22: =AL22+3*100 -> 700 | AN22: =AM22 -> 700 | AO22: =AN22+AO21*300 -> 1600 | AP22: =AO22+AP21*300 -> 1600 | AQ22: =AP22+AQ21*300 -> 1600 | AR22: =AQ22+AR21*300 -> 1600 | AS22: =AR22+AS21*300 -> 1600 | AT22: =AS22+AT21*300 -> 1600 | AU22: =AT22+AU21*300 -> 2200 | AV22: =AU22 -> 2200 | AW22: =AV22 -> 2200 | AX22: =AW22 -> 2200 | AY22: =AX22 -> 2200 | AZ22: =AY22 -> 2200 | BA22: =AZ22 -> 2200 | BB22: =BA22 -> 2200 | BC22: =BB22 -> 2200 | ... BY22: =BX22 -> 2200 | BZ22: =BY22+BZ21*200 -> 2600 | CA22: =BZ22 -> 2600 | CB22: =CA22 -> 2600 | CC22: =CB22 -> 2600 | CD22: =CC22 -> 2600 | CE22: =CD22 -> 2600
B23: 📜 | D23: dipendente Kanemura | AD23: -330 | AE23: -330 | AF23: -330 | AG23: -330 | AH23: -330 | AI23: -330 | AJ23: -330 | AK23: -330 | AL23: -330 | AM23: -330 | AN23: -330 | AO23: -330 | AP23: -330 | AQ23: -330 | AR23: -330 | AS23: -330 | AT23: -330 | AU23: -330 | AV23: -330 | AW23: -330 | AX23: -330 | AY23: -330 | AZ23: -330 | BA23: -330 | BB23: -330 | BC23: -330 | BD23: -330 | BE23: -330 | BF23: -330 | BG23: -330 | BH23: -330 | BI23: -330 | BJ23: -330 | BK23: -330 | BL23: -330 | BM23: -330 | BN23: -330 | BO23: -330 | BP23: -330 | BQ23: -330 | BR23: -330 | BS23: -330 | BT23: -330 | BU23: -330 | BV23: -330 | BW23: -330 | BX23: -330 | BY23: -330 | BZ23: -330 | CA23: -330 | CB23: -330 | CC23: -330 | CD23: -330 | CE23: -330
B24: 📜 | D24: dipendente Takamura | AD24: -330 | AE24: -330 | AF24: -330 | AG24: -330 | AH24: -330 | AI24: -330 | AJ24: -330 | AK24: -330 | AL24: -330 | AM24: -330 | AN24: -330 | AO24: -330 | AP24: -330 | AQ24: -330 | AR24: -330 | AS24: -330 | AT24: -330 | AU24: -330 | AV24: -330 | AW24: -330 | AX24: -330 | AY24: -330 | AZ24: -330 | BA24: -330 | BB24: -330 | BC24: -330 | BD24: -330 | BE24: -330 | BF24: -330 | BG24: -330 | BH24: -330 | BI24: -330 | BJ24: -330 | BK24: -330 | BL24: -330 | BM24: -330 | BN24: -330 | BO24: -330 | BP24: -330 | BQ24: -330 | BR24: -330 | BS24: -330 | BT24: -330 | BU24: -330 | BV24: -330 | BW24: -330 | BX24: -330 | BY24: -330 | BZ24: -330 | CA24: -330 | CB24: -330 | CC24: -330 | CD24: -330 | CE24: -330
B25: 📜 | D25: dipendente Umihana | AD25: -330 | AE25: -330 | AF25: -330 | AG25: -330 | AH25: -330 | AI25: -330 | AJ25: -330 | AK25: -330 | AL25: -330 | AM25: -330 | AN25: -330 | AO25: -330 | AP25: -330 | AQ25: -330 | AR25: -330 | AS25: -330 | AT25: -330 | AU25: -330 | AV25: -330 | AW25: -330 | AX25: -330 | AY25: -330 | AZ25: -330 | BA25: -330 | BB25: -330 | BC25: -330 | BD25: -330 | BE25: -330 | BF25: -330 | BG25: -330 | BH25: -330 | BI25: -330 | BJ25: -330 | BK25: -330 | BL25: -330 | BM25: -330 | BN25: -330 | BO25: -330 | BP25: -330 | BQ25: -330 | BR25: -330 | BS25: -330 | BT25: -330 | BU25: -330 | BV25: -330 | BW25: -330 | BX25: -330 | BY25: -330 | BZ25: -330 | CA25: -330 | CB25: -330 | CC25: -330 | CD25: -330 | CE25: -330
B26: 📜 | D26: dipendente Kanemura | AS26: -330 | AT26: -330 | AU26: -330 | AV26: -330 | AW26: -330 | AX26: -330 | AY26: -330 | AZ26: -330 | BA26: -330 | BB26: -330 | BC26: -330 | BD26: -330 | BE26: -330 | BF26: -330 | BG26: -330 | BH26: -330 | BI26: -330 | BJ26: -330 | BK26: -330 | BL26: -330 | BM26: -330 | BN26: -330 | BO26: -330 | BP26: -330 | BQ26: -330 | BR26: -330 | BS26: -330 | BT26: -330 | BU26: -330 | BV26: -330 | BW26: -330 | BX26: -330 | BY26: -330 | BZ26: -330 | CA26: -330 | CB26: -330 | CC26: -330 | CD26: -330 | CE26: -330
D28: Impiego
D29: Cameriera (terminato)
D30: Salario | F30: 223 | G30: 256 | H30: 295
CD31: premio Daimyo | CE31: =10000/4 -> 2500
AO32: miglioramento business (1 bianco +300)
E33: Bottino di partenza | O33: anello della nobildonna della missione | U33: vestito | AF33: tip dalle amiche | AG33: -50 | AI33: info | AJ33: -30 | AL33: info | AM33: -70 | AO33: info | AP33: -30 | AQ33: katana 941 | AR33: -20
E34: 5000 | O34: -350 | U34: -600 | AI34: info | AJ34: -50
O35: 350 | AF35: Masanori | AG35: -120 | AO35: info covo pirati | AP35: 150
I36: bribe info | Q36: bribe info | U36: orecchini e fermaglio | AL36: prestito | AM36: 5000 | AX36: ritorno prestito | AY36: =-5000*1.03 -> -5150
I37: =-10*3 -> -30 | Q37: -50 | U37: -200
AO38: todo prestito 10 gold
C42: 280 | D42: salario

Sheet Kleit
D1: Kleit | F1: Aprile | G1: Maggio | H1: Giugno | I1: Luglio | J1: Agosto | K1: Settembre | L1: Ottobre | M1: Novembre | N1: Dicembre | O1: Gennaio | P1: Febbraio | Q1: Marzo | R1: Aprile | S1: Maggio | T1: Giugno | U1: Luglio | V1: Agosto | W1: Settembre | X1: Ottobre | Y1: Novembre | Z1: Dicembre | AA1: Gennaio | AB1: Febbraio | AC1: Marzo | AD1: Aprile | AE1: Maggio | AF1: Giugno | AG1: Luglio | AH1: Agosto | AI1: Settembre | AJ1: Ottobre | AK1: Novembre | AL1: Dicembre | AM1: Gennaio | AN1: Febbraio | AO1: Marzo | AP1: Aprile | AQ1: Maggio | AR1: Giugno | AS1: Luglio | AT1: Agosto | AU1: Settembre | AV1: Ottobre | AW1: Novembre | AX1: Dicembre | AY1: Gennaio | AZ1: Febbraio | BA1: Marzo | BB1: Aprile | BC1: Maggio | BD1: Giugno | BE1: Luglio | BF1: Agosto | BG1: Settembre | BH1: Ottobre | BI1: Novembre | BJ1: Dicembre | BK1: Gennaio | BL1: Febbraio | BM1: Marzo | BN1: Aprile | BO1: Maggio | BP1: Giugno | BQ1: Luglio | BR1: Agosto | BS1: Settembre | BT1: Ottobre | BU1: Novembre | BV1: Dicembre | BW1: Gennaio | BX1: Febbraio | BY1: Marzo | BZ1: Aprile | CA1: Maggio | CB1: Giugno | CC1: Luglio | CD1: Agosto | CE1: Settembre | CF1: Ottobre | CG1: Novembre | CH1: Dicembre | CI1: Gennaio | CJ1: Febbraio | CK1: Marzo | CL1: Aprile | CM1: Maggio | CN1: Giugno | CO1: Luglio | CP1: Agosto | CQ1: Settembre | CR1: Ottobre | CS1: Novembre | CT1: Dicembre
D2: Anno | F2: 1532 | G2: =F2+IF(G1="Gennaio",1,0) -> 1532 | H2: =G2+IF(H1="Gennaio",1,0) -> 1532 | I2: =H2+IF(I1="Gennaio",1,0) -> 1532 | J2: =I2+IF(J1="Gennaio",1,0) -> 1532 | K2: =J2+IF(K1="Gennaio",1,0) -> 1532 | L2: =K2+IF(L1="Gennaio",1,0) -> 1532 | M2: =L2+IF(M1="Gennaio",1,0) -> 1532 | N2: =M2+IF(N1="Gennaio",1,0) -> 1532 | ... CT2: =CS2+IF(CT1="Gennaio",1,0) -> 1539
D3: Mese in-game | F3: =E3+1 -> 1 | G3: =F3+1 -> 2 | H3: =G3+1 -> 3 | I3: =H3+1 -> 4 | J3: =I3+1 -> 5 | K3: =J3+1 -> 6 | L3: =K3+1 -> 7 | M3: =L3+1 -> 8 | ... CT3: =CS3+1 -> 93
AO4: =SUMIF(AO19:AO54, ">=0") -> 4218
C5: =MAX(F11:CE11) -> 1646.46 | D5: AV | E5: =ABS(E25) -> 400 | L5: =ABS(L36+L79)-L83 -> 3650 | X5: =ABS(X83) -> 5300 | AA5: =ABS(AA48+AA54) -> 8000 | AJ5: =ABS(AG76) -> 10000
C6: =MIN(F11:CE11) -> -9513.54 | D6: NAV | F6: =SUM($E5:F5)+F10 -> 5083.4 | G6: =SUM($E5:G5)+G10 -> 5166.8 | H6: =SUM($E5:H5)+H10 -> 5250.2 | I6: =SUM($E5:I5)+I10 -> 5475.5 | J6: =SUM($E5:J5)+J10 -> 5700.8 | K6: =SUM($E5:K5)+K10 -> 6111.1 | L6: =SUM($E5:L5)+L10 -> 6566.6 | M6: =SUM($E5:M5)+M10 -> 7022.1 | ... CE6: =SUM($E5:CE5)+CE10 -> 56313.86
D8: bisognosi | AG8: 5 | AH8: 5 | AI8: 5 | AJ8: 5 | AK8: 5 | AL8: 5 | AM8: 5 | AN8: 5 | AO8: 5 | AP8: 5 | AQ8: 5 | AR8: 5 | AS8: 5 | AT8: 5 | AU8: 5 | AV8: 5 | AW8: 5 | AX8: 5 | AY8: 5 | AZ8: 5 | BA8: 5 | BB8: 5 | BC8: 5 | BD8: 5 | BE8: 5 | BF8: 5 | BG8: 5 | BH8: 5 | BI8: 5 | BJ8: 5 | BK8: 5 | BL8: 5 | BM8: 5 | BN8: 5 | BO8: 5 | BP8: 5 | BQ8: 5 | BR8: 5 | BS8: 5 | BT8: 5 | BU8: 5 | BV8: 5 | BW8: 5 | BX8: 5 | BY8: 5 | BZ8: 6 | CA8: 7 | CB8: 8 | CC8: 9 | CD8: 10 | CE8: 11
D10: Liquidi | E10: =SUM(E14:E1048576) -> 4600 | F10: =E10+SUM(F14:F1048576) -> 4683.4 | G10: =F10+SUM(G14:G1048576) -> 4766.8 | H10: =G10+SUM(H14:H1048576) -> 4850.2 | I10: =H10+SUM(I14:I1048576) -> 5075.5 | J10: =I10+SUM(J14:J1048576) -> 5300.8 | K10: =J10+SUM(K14:K1048576) -> 5711.1 | L10: =K10+SUM(L14:L1048576) -> 2516.6 | M10: =L10+SUM(M14:M1048576) -> 2972.1 | ... CE10: =CD10+SUM(CE14:CE1048576) -> 28963.86
D11: Profitto netto | F11: =F10-E10 -> 83.4 | G11: =G10-F10 -> 83.4 | H11: =H10-G10 -> 83.4 | I11: =I10-H10 -> 225.3 | J11: =J10-I10 -> 225.3 | K11: =K10-J10 -> 410.3 | L11: =L10-K10 -> -3194.5 | M11: =M10-L10 -> 455.5 | ... CE11: =CE10-CD10 -> -209.78
D14: Cibo | F14: -280 | G14: -280 | H14: -280 | I14: -280 | J14: -280 | K14: -280 | L14: -280 | M14: -280 | N14: -280 | O14: -280 | P14: -280 | Q14: -280 | R14: -280 | S14: -280 | T14: -280 | U14: -280 | V14: -280 | W14: -280 | X14: -280 | Y14: -280 | Z14: -280 | AA14: -280 | AB14: -280 | AC14: -280 | AD14: -280 | AE14: -280 | AF14: -280 | AG14: -280 | AH14: -280 | AI14: -280 | AJ14: -280 | AK14: -280 | AL14: -280 | AM14: -280 | AN14: -280 | AO14: -280 | AP14: -280 | AQ14: -280 | AR14: -280 | AS14: -280 | AT14: -280 | AU14: -280 | AV14: -280 | AW14: -280 | AX14: -280 | AY14: -280 | AZ14: -280 | BA14: -280 | BB14: -280 | BC14: -280 | BD14: -280 | BE14: -280 | BF14: -280 | BG14: -280 | BH14: -280 | BI14: -280 | BJ14: -280 | BK14: -280 | BL14: -280 | BM14: -280 | BN14: -280 | BO14: -280 | BP14: -280 | BQ14: -280 | BR14: -280 | BS14: -280 | BT14: -280 | BU14: -280 | BV14: -280 | BW14: -280 | BX14: -280 | BY14: -280 | BZ14: -280 | CA14: -280 | CB14: -280 | CC14: -280 | CD14: -280 | CE14: -280
D15: Affitto | F15: -190 | G15: -190 | H15: -190 | I15: -190 | J15: -190 | K15: -190 | L15: -190 | M15: -190 | N15: -190 | O15: -190 | P15: -190 | Q15: -190 | R15: -190 | S15: -190 | T15: -190 | U15: -190 | V15: -190 | W15: -190 | X15: -190 | Y15: -190 | Z15: -190 | AA15: -190 | AB15: -190 | AC15: -190 | AD15: -190 | AE15: -190 | AF15: -190 | AG15: -190 | AH15: -190 | AI15: -190 | AJ15: -190 | AK15: -190 | AL15: -190 | AM15: -190 | AN15: -190 | AO15: -190 | AP15: -190 | AQ15: -190 | AR15: -190 | AS15: -190 | AT15: -190 | AU15: -190 | AV15: -190 | AW15: -190 | AX15: -190 | AY15: -190 | AZ15: -190 | BA15: -190 | BB15: -190 | BC15: -190 | BD15: -190 | BE15: -190 | BF15: -190 | BG15: -190 | BH15: -190 | BI15: -190 | BJ15: -190 | BK15: -190 | BL15: -190 | BM15: -190 | BN15: -190 | BO15: -190 | BP15: -190 | BQ15: -190 | BR15: -190 | BS15: -190 | BT15: -190 | BU15: -190 | BV15: -190 | BW15: -190 | BX15: -190 | BY15: -190 | BZ15: -190 | CA15: -190 | CB15: -190 | CC15: -190 | CD15: -190 | CE15: -190
B16: =COUNTA(B17:B78) -> 13 | C16: /13 | D16: Permessi
D18: Bancarella a Umihana
D19: Kleit - Maestro del tè | F19: =$C$86 -> 450 | G19: =$C$86 -> 450 | H19: =$C$86 -> 450 | I19: =$C$86 -> 450 | J19: =$C$86 -> 450 | K19: =$C$86 -> 450
B20: 👤 | D20: Apprendista 1 - prod. tè full-time bancarella | F20: =$C$86*$C$91 -> 270 | G20: =$C$86*$C$91 -> 270 | H20: =$C$86*$C$91 -> 270 | I20: =$C$86*$C$91 -> 270 | J20: =$C$86*$C$91 -> 270 | K20: =$C$86*$C$91 -> 270 | L20: 450 | M20: 450 | N20: 450 | O20: 450 | P20: 450 | Q20: 450 | R20: 450 | S20: 450 | T20: 450 | U20: 450 | V20: 450 | W20: 450 | X20: 450 | Y20: 450 | Z20: 450 | AA20: 450 | AB20: 450 | AC20: 450 | AD20: 450 | AE20: 450 | AF20: 450 | AG20: 450 | AH20: 450 | AI20: 450 | AJ20: 450 | AK20: 450 | AL20: 450 | AM20: 450 | AN20: 450 | AO20: 450 | AP20: 450 | AQ20: 450 | AR20: 450 | AS20: 450 | AT20: 450 | AU20: 450 | AV20: 450 | AW20: 450 | AX20: 450 | AY20: 450 | AZ20: 450 | BA20: 450 | BB20: 450 | BC20: 450 | BD20: 450 | BE20: 450 | BF20: 450 | BG20: 450 | BH20: 450 | BI20: 450 | BJ20: 450 | BK20: 450 | BL20: 450 | BM20: 450 | BN20: 450 | BO20: 450 | BP20: 450 | BQ20: 450 | BR20: 450 | BS20: 450 | BT20: 450 | BU20: 450 | BV20: 450 | BW20: 450 | BX20: 450 | BY20: 450 | BZ20: 450 | CA20: 450 | CB20: 450 | CC20: 450 | CD20: 450 | CE20: 450
D21: salario | F21: =-$C$92 -> -120 | G21: =-$C$92 -> -120 | H21: =-$C$92 -> -120 | I21: =-$C$92 -> -120 | J21: =-$C$92 -> -120 | K21: =-$C$92 -> -120 | L21: =-$C$93 -> -200 | M21: =-$C$93 -> -200 | N21: =-$C$93 -> -200 | O21: =-$C$93 -> -200 | P21: =-$C$93 -> -200 | Q21: =-$C$93 -> -200 | R21: =-$C$93 -> -200 | S21: =-$C$93 -> -200 | ... AI21: =-$C$93 -> -200 | AJ21: -400 | AK21: -400 | AL21: -400 | AM21: -400 | AN21: -400 | AO21: -400 | AP21: -400 | AQ21: -400 | AR21: -400 | AS21: -400 | AT21: -400 | AU21: -400 | AV21: -400 | AW21: -400 | AX21: -400 | AY21: -400 | AZ21: -400 | BA21: -400 | BB21: -400 | BC21: -400 | BD21: -400 | BE21: -400 | BF21: -400 | BG21: -400 | BH21: -400 | BI21: -400 | BJ21: -400 | BK21: -400 | BL21: -400 | BM21: -400 | BN21: -400 | BO21: -400 | BP21: -400 | BQ21: -400 | BR21: -400 | BS21: -400 | BT21: -400 | BU21: -400 | BV21: -400 | BW21: -400 | BX21: -400 | BY21: -400 | BZ21: -400 | CA21: -400 | CB21: -400 | CC21: -400 | CD21: -400 | CE21: -400
D22: Apprendista 2 - prod. tè full-time bancarella | I22: =$C$86*$C$91 -> 270 | J22: =$C$86*$C$91 -> 270 | K22: =$C$86*$C$91 -> 270
D23: salario | I23: =-$C$92 -> -120 | J23: =-$C$92 -> -120 | K23: =-$C$92 -> -120
B24: 📜 | F24: =-$C$94 -> -25 | G24: =-$C$94 -> -25 | H24: =-$C$94 -> -25 | I24: =-$C$94 -> -25 | J24: =-$C$94 -> -25 | K24: =-$C$94 -> -25 | L24: =-$C$94 -> -25 | M24: =-$C$94 -> -25 | ... CE24: =-$C$94 -> -25
D25: Attrezzi per il tè | E25: -400
D28: Taverna
C29: ⭐️ | D29: Kleit - Cuoco e bartender Taverna | L29: =$C88 -> 600 | M29: =$C88 -> 600 | N29: =$C88 -> 600 | O29: =$C88 -> 600 | P29: =$C88 -> 600 | Q29: =$C88 -> 600 | R29: =$C88 -> 600 | S29: =$C88 -> 600 | T29: =$C88 -> 600 | U29: =$C$89 -> 700 | V29: =$C$89 -> 700 | W29: =$C$89 -> 700 | X29: =$C$89 -> 700 | Y29: =$C$89 -> 700 | Z29: =$C$89 -> 700 | AA29: =$C$89 -> 700 | AB29: =$C$89 -> 700 | ... CE29: =$C$89 -> 700
B30: 👤 | D30: Apprendista 2 - prod. tè full-time bancarella | L30: =$C88 -> 600 | M30: =$C88 -> 600 | N30: =$C88 -> 600 | O30: =$C88 -> 600 | P30: =$C88 -> 600 | Q30: =$C88 -> 600 | R30: =$C88 -> 600 | S30: =$C88 -> 600 | T30: =$C88 -> 600 | U30: =$C$89 -> 700 | V30: =$C$89 -> 700 | W30: =$C$89 -> 700 | X30: =$C$89 -> 700 | Y30: =$C$89 -> 700 | Z30: =$C$89 -> 700 | AA30: =$C$89 -> 700 | AB30: =$C$89 -> 700 | ... CE30: =$C$89 -> 700
B31: 👤 | D31: Apprendista 3 - prod. tè full-time bancarella | AA31: =$C$89 -> 700 | AB31: =$C$89 -> 700 | AC31: =$C$89 -> 700 | AD31: =$C$89 -> 700 | AE31: =$C$89 -> 700 | AF31: =$C$89 -> 700 | AG31: =$C$89 -> 700 | AH31: =$C$89 -> 700 | ... CE31: =$C$89 -> 700
D33: salario | L33: =-$C$96 -> -350 | M33: =-$C$96 -> -350 | N33: =-$C$96 -> -350 | O33: =-$C$96 -> -350 | P33: =-$C$96 -> -350 | Q33: =-$C$96 -> -350 | R33: =-$C$96 -> -350 | S33: =-$C$96 -> -350 | ... AI33: =-$C$96 -> -350 | AJ33: -400 | AK33: -400 | AL33: -400 | AM33: -400 | AN33: -400 | AO33: -400 | AP33: -400 | AQ33: -400 | AR33: -400 | AS33: -400 | AT33: -400 | AU33: -400 | AV33: -400 | AW33: -400 | AX33: -400 | AY33: -400 | AZ33: -400 | BA33: -400 | BB33: -400 | BC33: -400 | BD33: -400 | BE33: -400 | BF33: -400 | BG33: -400 | BH33: -400 | BI33: -400 | BJ33: -400 | BK33: -400 | BL33: -400 | BM33: -400 | BN33: -400 | BO33: -400 | BP33: -400 | BQ33: -400 | BR33: -400 | BS33: -400 | BT33: -400 | BU33: -400 | BV33: -400 | BW33: -400 | BX33: -400 | BY33: -400 | BZ33: -400 | CA33: -400 | CB33: -400 | CC33: -400 | CD33: -400 | CE33: -400
D34: salario | AA34: =-$C$96 -> -350 | AB34: =-$C$96 -> -350 | AC34: =-$C$96 -> -350 | AD34: =-$C$96 -> -350 | AE34: =-$C$96 -> -350 | AF34: =-$C$96 -> -350 | AG34: =-$C$96 -> -350 | AH34: =-$C$96 -> -350 | AI34: =-$C$96 -> -350 | AJ34: -400 | AK34: -400 | AL34: -400 | AM34: -400 | AN34: -400 | AO34: -400 | AP34: -400 | AQ34: -400 | AR34: -400 | AS34: -400 | AT34: -400 | AU34: -400 | AV34: -400 | AW34: -400 | AX34: -400 | AY34: -400 | AZ34: -400 | BA34: -400 | BB34: -400 | BC34: -400 | BD34: -400 | BE34: -400 | BF34: -400 | BG34: -400 | BH34: -400 | BI34: -400 | BJ34: -400 | BK34: -400 | BL34: -400 | BM34: -400 | BN34: -400 | BO34: -400 | BP34: -400 | BQ34: -400 | BR34: -400 | BS34: -400 | BT34: -400 | BU34: -400 | BV34: -400 | BW34: -400 | BX34: -400 | BY34: -400 | BZ34: -400 | CA34: -400 | CB34: -400 | CC34: -400 | CD34: -400 | CE34: -400
B35: 📜 | D35: Tassa Taverna | L35: =-$C97 -> -100 | M35: =-$C97 -> -100 | N35: =-$C97 -> -100 | O35: =-$C97 -> -100 | P35: =-$C97 -> -100 | Q35: =-$C97 -> -100 | R35: =-$C97 -> -100 | S35: =-$C97 -> -100 | ... CE35: =-$C97 -> -100
K36: Taverna Umihana | L36: -8400
Z37: concorrenza | AA37: =AA33*0.2 -> -70 | AB37: =AB33*0.2 -> -70 | AC37: =AC33*0.2 -> -70 | AD37: =AD33*0.2 -> -70 | AE37: =AE33*0.2 -> -70 | AF37: =AF33*0.2 -> -70 | AG37: =AG33*0.2 -> -70 | AH37: =AH33*0.2 -> -70 | AJ37: =AJ33*0.2 -> -80 | AK37: =AK33*0.2 -> -80
D39: Tratta 1 (U-K)
D40: Marinaio, Apprendista mercante | O40: =$C$87*$C$90 -> 660 | P40: =$C$87*$C$90 -> 660 | Q40: =$C$87*$C$90 -> 660 | R40: =$C$87*$C$90 -> 660 | S40: =$C$87*$C$90 -> 660 | T40: =$C$87*$C$90 -> 660 | U40: =$C$87*$C$90 -> 660 | V40: =$C$87*$C$90 -> 660 | ... AR40: =$C$87*$C$90 -> 660
D41: Tassa rotta commerciale | O41: =-$C$95 -> -320 | P41: =-$C$95 -> -320 | Q41: =-$C$95 -> -320 | R41: =-$C$95 -> -320 | S41: =-$C$95 -> -320 | T41: =-$C$95 -> -320 | U41: =-$C$95 -> -320 | V41: =-$C$95 -> -320 | ... AI41: =-$C$95 -> -320 | AJ41: -400 | AK41: -400 | AL41: -400 | AM41: -400 | AN41: -400 | AO41: -400 | AP41: -400 | AQ41: -400 | AR41: -400
D45: Tratta 2 (U-T)
B46: 👤 | D46: Marinaio, Apprendista mercante | AA46: =$C$87*$C$90 -> 660 | AB46: =$C$87*$C$90 -> 660 | AC46: =$C$87*$C$90 -> 660 | AD46: =$C$87*$C$90 -> 660 | AE46: =$C$87*$C$90 -> 660 | AF46: =$C$87*$C$90 -> 660 | AG46: =$C$87*$C$90 -> 660 | AH46: =$C$87*$C$90 -> 660 | ... CE46: =$C$87*$C$90 -> 660
B47: 📜 | D47: Tassa rotta commerciale | AA47: =-$C$95 -> -320 | AB47: =-$C$95 -> -320 | AC47: =-$C$95 -> -320 | AD47: =-$C$95 -> -320 | AE47: =-$C$95 -> -320 | AF47: =-$C$95 -> -320 | AG47: =-$C$95 -> -320 | AH47: =-$C$95 -> -320 | AI47: =-$C$95 -> -320 | AJ47: -400 | AK47: -400 | AL47: -400 | AM47: -400 | AN47: -400 | AO47: -400 | AP47: -400 | AQ47: -400 | AR47: -400 | AS47: -400 | AT47: -400 | AU47: -400 | AV47: -400 | AW47: -400 | AX47: -400 | AY47: -400 | AZ47: -400 | BA47: -400 | BB47: -400 | BC47: -400 | BD47: -400 | BE47: -400 | BF47: -400 | BG47: -400 | BH47: -400 | BI47: -400 | BJ47: -400 | BK47: -400 | BL47: -400 | BM47: -400 | BN47: -400 | BO47: -400 | BP47: -400 | BQ47: -400 | BR47: -400 | BS47: -400 | BT47: -400 | BU47: -400 | BV47: -400 | BW47: -400 | BX47: -400 | BY47: -400 | BZ47: -399 | CA47: -398 | CB47: -397 | CC47: -396 | CD47: -395 | CE47: -394
Z48: Barca media | AA48: -3000
D51: Magazzino medio a Hakusui (rotte 1, 2, 3)
B52: 📜 | D52: Boost vendite | AA52: =(AA46+AA40)*$C$99+SUM(AA29:AA32)*$C$100 -> 348 | AB52: =(AB46+AB40)*$C$99+SUM(AB29:AB32)*$C$100 -> 348 | AC52: =(AC46+AC40)*$C$99+SUM(AC29:AC32)*$C$100 -> 348 | AD52: =(AD46+AD40)*$C$99+SUM(AD29:AD32)*$C$100 -> 348 | AE52: =(AE46+AE40)*$C$99+SUM(AE29:AE32)*$C$100 -> 348 | AF52: =(AF46+AF40)*$C$99+SUM(AF29:AF32)*$C$100 -> 348 | AG52: =(AG46+AG40)*$C$99+SUM(AG29:AG32)*$C$100 -> 348 | AH52: =(AH46+AH40)*$C$99+SUM(AH29:AH32)*$C$100 -> 348 | ... CE52: =(CE46+CE40)*$C$99+SUM(CE29:CE32)*$C$100 -> 216
B53: 👤 | D53: Mantenimento | AA53: -350 | AB53: =AA53 -> -350 | AC53: =AB53 -> -350 | AD53: =AC53 -> -350 | AE53: =AD53 -> -350 | AF53: =AE53 -> -350 | AG53: =AF53 -> -350 | AH53: =AG53 -> -350 | AI53: =AH53 -> -350 | ... CE53: =CD53 -> -350
D54: Prezzo magazzino | Z54: Magazzino Umihana | AA54: -5000
D57: Associazione Tsuki no Tsuyu (Rugiada di Luna)
D58: donazione associazione pescatori Takamura | AD58: -100 | AE58: -100 | AF58: -100 | AG58: -100 | AH58: -100 | AI58: -100 | AJ58: -100 | AK58: -100 | AL58: -100 | AM58: -100 | AN58: -100 | AO58: -100 | AP58: -100 | AQ58: -100 | AR58: -100 | AS58: -100 | AT58: -100 | AU58: -100 | AV58: -100 | AW58: -100 | AX58: -100 | AY58: -100 | AZ58: -100 | BA58: -100 | BB58: -100 | BC58: -100 | BD58: -100 | BE58: -100 | BF58: -100 | BG58: -100 | BH58: -100 | BI58: -100 | BJ58: -100 | BK58: -100 | BL58: -100 | BM58: -100 | BN58: -100 | BO58: -100 | BP58: -100 | BQ58: -100 | BR58: -100 | BS58: -100 | BT58: -100 | BU58: -100 | BV58: -100 | BW58: -100 | BX58: -100 | BY58: -100 | BZ58: -100 | CA58: -100 | CB58: -100 | CC58: -100 | CD58: -100 | CE58: -100
D59: donazione tempio Umihana | AG59: -100 | AH59: -100 | AI59: -100 | AJ59: -100 | AK59: -100 | AL59: -100 | AM59: -100 | AN59: -100 | AO59: -100 | AP59: -100 | AQ59: -100 | AR59: -100 | AS59: -100 | AT59: -100 | AU59: -100 | AV59: -100 | AW59: -100 | AX59: -100 | AY59: -100 | AZ59: -100 | BA59: -100 | BB59: -100 | BC59: -100 | BD59: -100 | BE59: -100 | BF59: -100 | BG59: -100 | BH59: -100 | BI59: -100 | BJ59: -100 | BK59: -100 | BL59: -100 | BM59: -100 | BN59: -100 | BO59: -100 | BP59: -100 | BQ59: -100 | BR59: -100 | BS59: -100 | BT59: -100 | BU59: -100 | BV59: -100 | BW59: -100 | BX59: -100 | BY59: -100 | BZ59: -100 | CA59: -100 | CB59: -100 | CC59: -100 | CD59: -100 | CE59: -100
B61: 👤 | D61: Capitano | AG61: -1000 | AH61: -1000 | AI61: -1000 | AJ61: -1000 | AK61: -1000 | AL61: -1000 | AM61: -500 | AN61: -500 | AO61: -500 | AP61: -500 | AQ61: -500 | AR61: -500 | AS61: -500 | AT61: -500 | AU61: -500 | AV61: -500 | AW61: -500 | AX61: -500 | AY61: -500 | AZ61: -500 | BA61: -500 | BB61: -500 | BC61: -500 | BD61: -500 | BE61: -500 | BF61: -500 | BG61: -500 | BH61: -500 | BI61: -500 | BJ61: -500 | BK61: -500 | BL61: -500 | BM61: -500 | BN61: -500 | BO61: -500 | BP61: -500 | BQ61: -500 | BR61: -500 | BS61: -500 | BT61: -500 | BU61: -500 | BV61: -500 | BW61: -500 | BX61: -500 | BY61: -500 | BZ61: -500 | CA61: -500 | CB61: -500 | CC61: -500 | CD61: -500 | CE61: -500
B62: 👤 | D62: Medico | AG62: -700 | AH62: -700 | AI62: -700 | AJ62: -700 | AK62: -700 | AL62: -700 | AM62: -700 | AN62: -700 | AO62: -700 | AP62: -700 | AQ62: -700 | AR62: -700 | AS62: -700 | AT62: -700 | AU62: -700 | AV62: -700 | AW62: -700 | AX62: -700 | AY62: -700 | AZ62: -700 | BA62: -700 | BB62: -700 | BC62: -700 | BD62: -700 | BE62: -700 | BF62: -700 | BG62: -700 | BH62: -700 | BI62: -700 | BJ62: -700 | BK62: -700 | BL62: -700 | BM62: -700 | BN62: -700 | BO62: -700 | BP62: -700 | BQ62: -700 | BR62: -700 | BS62: -700 | BT62: -700 | BU62: -700 | BV62: -700 | BW62: -700 | BX62: -700 | BY62: -700 | BZ62: -700 | CA62: -700 | CB62: -700 | CC62: -700 | CD62: -700 | CE62: -700
D63: servizio medico | AG63: 100 | AH63: 100 | AI63: 100 | AJ63: 100 | AK63: 100 | AL63: 100 | AM63: 100 | AN63: 100 | AO63: 100 | AP63: 100 | AQ63: 100 | AR63: 100 | AS63: 100 | AT63: 100 | AU63: 100 | AV63: 100 | AW63: 100 | AX63: 100 | AY63: 100 | AZ63: 100 | BA63: 100 | BB63: 100 | BC63: 100 | BD63: 100 | BE63: 100 | BF63: 100 | BG63: 100 | BH63: 100 | BI63: 100 | BJ63: 100 | BK63: 100 | BL63: 100 | BM63: 100 | BN63: 100 | BO63: 100 | BP63: 100 | BQ63: 100 | BR63: 100 | BS63: 100 | BT63: 100 | BU63: 100 | BV63: 100 | BW63: 100 | BX63: 100 | BY63: 100 | BZ63: 100 | CA63: 100 | CB63: 100 | CC63: 100 | CD63: 100 | CE63: 100
D64: Guardia
B65: 👤 | D65: Cuoco | AR65: -500 | AS65: -500 | AT65: -500 | AU65: -500 | AV65: -500 | AW65: -500 | AX65: -500 | AY65: -500 | AZ65: -500 | BA65: -500 | BB65: -500 | BC65: -500 | BD65: -500 | BE65: -500 | BF65: -500 | BG65: -500 | BH65: -500 | BI65: -500 | BJ65: -500 | BK65: -500 | BL65: -500 | BM65: -500 | BN65: -500 | BO65: -500 | BP65: -500 | BQ65: -500 | BR65: -500 | BS65: -500 | BT65: -500 | BU65: -500 | BV65: -500 | BW65: -500 | BX65: -500 | BY65: -500 | BZ65: -500 | CA65: -500 | CB65: -500 | CC65: -500 | CD65: -500 | CE65: -500
B66: 👤 | D66: Cameriere | AR66: -400 | AS66: -400 | AT66: -400 | AU66: -400 | AV66: -400 | AW66: -400 | AX66: -400 | AY66: -400 | AZ66: -400 | BA66: -400 | BB66: -400 | BC66: -400 | BD66: -400 | BE66: -400 | BF66: -400 | BG66: -400 | BH66: -400 | BI66: -400 | BJ66: -400 | BK66: -400 | BL66: -400 | BM66: -400 | BN66: -400 | BO66: -400 | BP66: -400 | BQ66: -400 | BR66: -400 | BS66: -400 | BT66: -400 | BU66: -400 | BV66: -400 | BW66: -400 | BX66: -400 | BY66: -400 | BZ66: -400 | CA66: -400 | CB66: -400 | CC66: -400 | CD66: -400 | CE66: -400
D67: cibo | AG67: =-200*AG8 -> -1000 | AH67: =-200*AH8 -> -1000 | AI67: =-200*AI8 -> -1000 | AJ67: =-200*AJ8 -> -1000 | AK67: =-200*AK8 -> -1000 | AL67: =-200*AL8 -> -1000 | AM67: =-200*AM8 -> -1000 | AN67: =-200*AN8 -> -1000 | ... CE67: =-200*CE8 -> -2200
D68: Vendita tè e cibo | AG68: =-1.1*AG67 -> 1100 | AH68: =-1.1*AH67 -> 1100 | AI68: =-1.1*AI67 -> 1100 | AJ68: =-1.1*AJ67 -> 1100 | AK68: =-1.1*AK67 -> 1100 | AL68: =-1.1*AL67 -> 1100 | AM68: =-1.1*AM67 -> 1100 | AN68: =-1.1*AN67 -> 1100 | ... AQ68: =-1.1*AQ67 -> 1100 | AR68: 3500 | AS68: 3500 | AT68: 3500 | AU68: 3500 | AV68: 3500 | AW68: 3500 | AX68: 3500 | AY68: 3500 | AZ68: 3500 | BA68: 3500 | BB68: 3500 | BC68: 3500 | BD68: 3500 | BE68: 3500 | BF68: 3500 | BG68: 3500 | BH68: 3500 | BI68: 3500 | BJ68: 3500 | BK68: 3500 | BL68: 3500 | BM68: 3500 | BN68: 3500 | BO68: 3500 | BP68: 3500 | BQ68: 3500 | BR68: 3500 | BS68: 3500 | BT68: 3500 | BU68: 3500 | BV68: 3500 | BW68: 3500 | BX68: 3500 | BY68: 3500 | BZ68: 3501 | CA68: 3502 | CB68: 3503 | CC68: 3504 | CD68: 3505 | CE68: 3506
AL69: todo update | AM69: todo vendita pesce
D71: Assicurazione Gilda del Gusto | F71: =-SUMIF(F19:F54, ">=0")*$C$102 -> -21.6 | G71: =-SUMIF(G19:G54, ">=0")*$C$102 -> -21.6 | H71: =-SUMIF(H19:H54, ">=0")*$C$102 -> -21.6 | I71: =-SUMIF(I19:I54, ">=0")*$C$102 -> -29.7 | J71: =-SUMIF(J19:J54, ">=0")*$C$102 -> -29.7 | K71: =-SUMIF(K19:K54, ">=0")*$C$102 -> -29.7 | L71: =-SUMIF(L19:L54, ">=0")*$C$102 -> -49.5 | M71: =-SUMIF(M19:M54, ">=0")*$C$102 -> -49.5 | ... CE71: =-SUMIF(CE19:CE54, ">=0")*$C$102 -> -102.78
AG72: =$AG$76*$C$102/3 -> -100 | AH72: =$AG$76*$C$102/3 -> -100 | AI72: =$AG$76*$C$102/3 -> -100 | AJ72: =$AG$76*$C$102/3 -> -100 | AK72: =$AG$76*$C$102/3 -> -100 | AL72: =$AG$76*$C$102/3 -> -100 | AM72: =$AG$76*$C$102/3 -> -100 | AN72: =$AG$76*$C$102/3 -> -100 | ... CE72: =$AG$76*$C$102/3 -> -100
AR75: todo tè Kleit | AU75: todo ristorante
AF76: Barca Enorme | AG76: -10000 | AI76: torneo arco | AJ76: 200 | BY76: riparazioni tsunami | BZ76: -10000
E77: Bottino di partenza | M77: todo buff taverna | R77: donazioni templi Umihana Takamura | AF77: Allestimento | AG77: -600 | AQ77: vendita sake | AR77: 300 | AU77: todo boost vendite ristorante
E78: 5000 | L78: Set da tè | R78: -200 | AC78: amuletini | AD78: -5
L79: -250 | AF79: Sussidio Daimyo | AG79: =-(AG62+AG61+AG67)/2 -> 1350 | AH79: =-(AH62+AH61+AH67)/2 -> 1350 | AI79: =-(AI62+AI61+AI67)/2 -> 1350 | AJ79: =-(AJ62+AJ61+AJ67)/2 -> 1350 | AK79: =-(AK62+AK61+AK67)/2 -> 1350 | AL79: =-(AL62+AL61+AL67)/2 -> 1350
AC80: stuck at library and cave | AD80: =-1200/30*2 -> -80
K82: vendite extra al festival | L82: prestito | X82: prestito
K83: 185 | L83: 5000 | X83: -5300
C86: 450 | D86: Mercanti bancarelle
C87: 1100 | D87: rotta marittima
C88: 600 | D88: prod. Dipendente taverna
C89: 700
C90: 0.6 | D90: apprendista mercante multiplier
C91: 0.6 | D91: apprendista full-time multiplier
C92: 120 | D92: salario dipendente part-time
C93: 200 | D93: salario dipendente full-time
C94: 25 | D94: Tassa bancarella
C95: 320 | D95: paga marinaio+mercante
C96: 350 | D96: salario dipendente taverna full-time
C97: 100 | D97: Tassa Taverna
C99: 0.2 | D99: boost vendite magazzino
C100: 0.04 | D100: boost vendite magazzino (taverna)
C102: 0.03 | D102: Assicurazione

Sheet Economia
B1: 1 | C1: =B1+1 -> 2 | D1: =C1+1 -> 3 | E1: =D1+1 -> 4 | F1: =E1+1 -> 5 | G1: =F1+1 -> 6 | H1: =G1+1 -> 7 | I1: =H1+1 -> 8 | J1: =I1+1 -> 9 | ... CA1: =BZ1+1 -> 78
A2: Nic | B2: =Nic!D6/100 -> 51.8 | C2: =Nic!E6/100 -> 54.5 | D2: =Nic!F6/100 -> 57.2 | E2: =Nic!G6/100 -> 59.9 | F2: =Nic!H6/100 -> 62.6 | G2: =Nic!I6/100 -> 65.3 | H2: =Nic!J6/100 -> 68 | I2: =Nic!K6/100 -> 70.7 | ... CA2: =Nic!CC6/100 -> 648.21
A3: Cris | B3: =Cris!D6/100 -> 42.35 | C3: =Cris!E6/100 -> 45.14 | D3: =Cris!F6/100 -> 48.03 | E3: =Cris!G6/100 -> 51.56 | F3: =Cris!H6/100 -> 54.92 | G3: =Cris!I6/100 -> 58.33 | H3: =Cris!J6/100 -> 61.47 | I3: =Cris!K6/100 -> 64.65 | ... CA3: =Cris!CC6/100 -> 670.88
A4: Peter | B4: =Peter!D6/100 -> 54.27 | C4: =Peter!E6/100 -> 59.14 | D4: =Peter!F6/100 -> 64.01 | E4: =Peter!G6/100 -> 71.332 | F4: =Peter!H6/100 -> 78.654 | G4: =Peter!I6/100 -> 85.976 | H4: =Peter!J6/100 -> 96 | I4: =Peter!K6/100 -> 116.024 | ... CA4: =Peter!CC6/100 -> 846.4246
A5: Kleit | B5: =Kleit!F6/100 -> 50.834 | C5: =Kleit!G6/100 -> 51.668 | D5: =Kleit!H6/100 -> 52.502 | E5: =Kleit!I6/100 -> 54.755 | F5: =Kleit!J6/100 -> 57.008 | G5: =Kleit!K6/100 -> 61.111 | H5: =Kleit!L6/100 -> 65.666 | I5: =Kleit!M6/100 -> 70.221 | ... CA5: =Kleit!CE6/100 -> 563.1386
A6: Zilla | B6: =Zilla!H6/100 -> 56.02 | C6: =Zilla!I6/100 -> 62.04 | D6: =Zilla!J6/100 -> 67.326667 | E6: =Zilla!K6/100 -> 75.498667 | F6: =Zilla!L6/100 -> 83.304 | G6: =Zilla!M6/100 -> 91.476 | H6: =Zilla!N6/100 -> 101.8 | I6: =Zilla!O6/100 -> 112.124 | ... AY6: =Zilla!BE6/100 -> 664.55406 | AZ6: =(Zilla!BF6/100+Vito!BD6/100)/2 -> 460.2983 | BA6: =(Zilla!BG6/100+Vito!BE6/100)/2 -> 474.89957 | BB6: =(Zilla!BH6/100+Vito!BF6/100)/2 -> 489.50085 | BC6: =(Zilla!BI6/100+Vito!BG6/100)/2 -> 504.10212 | BD6: =(Zilla!BJ6/100+Vito!BH6/100)/2 -> 518.70339 | BE6: =(Zilla!BK6/100+Vito!BI6/100)/2 -> 533.30466 | BF6: =(Zilla!BL6/100+Vito!BJ6/100)/2 -> 547.90593 | BG6: =(Zilla!BM6/100+Vito!BK6/100)/2 -> 562.5072 | ... CA6: =(Zilla!CG6/100+Vito!CE6/100)/2 -> 846.81763
A7: Vito | B7: =Vito!F6/100 -> 52.23 | C7: =Vito!G6/100 -> 54.79 | D7: =Vito!H6/100 -> 57.74 | E7: =Vito!I6/100 -> 60.24 | F7: =Vito!J6/100 -> 63.04 | G7: =Vito!K6/100 -> 65.84 | H7: =Vito!L6/100 -> 68.64 | I7: =Vito!M6/100 -> 71.44 | ... AY7: =Vito!BC6/100 -> 226.84 | AZ7: =(Zilla!BF6/100+Vito!BD6/100)/2 -> 460.2983 | BA7: =(Zilla!BG6/100+Vito!BE6/100)/2 -> 474.89957 | BB7: =(Zilla!BH6/100+Vito!BF6/100)/2 -> 489.50085 | BC7: =(Zilla!BI6/100+Vito!BG6/100)/2 -> 504.10212 | BD7: =(Zilla!BJ6/100+Vito!BH6/100)/2 -> 518.70339 | BE7: =(Zilla!BK6/100+Vito!BI6/100)/2 -> 533.30466 | BF7: =(Zilla!BL6/100+Vito!BJ6/100)/2 -> 547.90593 | BG7: =(Zilla!BM6/100+Vito!BK6/100)/2 -> 562.5072 | ... CA7: =(Zilla!CG6/100+Vito!CE6/100)/2 -> 846.81763
A8: Team Villa | AZ8: =(Zilla!BF6/100+Vito!BD6/100)/2 -> 460.2983 | BA8: =(Zilla!BG6/100+Vito!BE6/100)/2 -> 474.89957 | BB8: =(Zilla!BH6/100+Vito!BF6/100)/2 -> 489.50085 | BC8: =(Zilla!BI6/100+Vito!BG6/100)/2 -> 504.10212 | BD8: =(Zilla!BJ6/100+Vito!BH6/100)/2 -> 518.70339 | BE8: =(Zilla!BK6/100+Vito!BI6/100)/2 -> 533.30466 | BF8: =(Zilla!BL6/100+Vito!BJ6/100)/2 -> 547.90593 | BG8: =(Zilla!BM6/100+Vito!BK6/100)/2 -> 562.5072 | ... CA8: =(Zilla!CG6/100+Vito!CE6/100)/2 -> 846.81763
N11: 45862 | O11: 45918
N13: word count | O13: word count
M14: NPC | N14: 25485 | O14: 32000
M15: PC | N15: 18937 | O15: 21400
M16: Github | N16: 9353 | O16: 10300
M17: Other | N17: =N18-SUM(N14:N16) -> 11296 | O17: =O18-SUM(O14:O16) -> 15000
M18: Shimanami | N18: 65071 | O18: 78700
C53: a2 | D53: 1000 | F53: =AVERAGE(D53:D54) -> 750 | I53: 1500 | J53: q/ha
C54: a1 | D54: 500 | F54: =(D53-D54)/2 -> 250 | I54: =I53/100 -> 15 | J54: kg/m^2
C55: b2 | D55: 9 | F55: =AVERAGE(D55:D56) -> 6.5 | I55: =I53/0.375*3.6/100 -> 144 | J55: Ryoo/Kawa
C56: b1 | D56: 4 | F56: =(D55-D56)/2 -> 2.5 | I56: =10000/40 -> 250 | J56: Kawa / contadino
C58: p2 | D58: =F58+F59 -> 8375 | F58: =F53*F55 -> 4875
C59: p1 | D59: =F58-F59 -> 1375 | F59: =F53*F56+F54*F55 -> 3500
C65: popolazione | D65: =3300 + 2100 + 1900 -> 7300
C66: prezzo riso | D66: 10
C67: consumo mensile (silver) | D67: 330
C68: consumo mesile (ryoo) | D68: =D67/D66 -> 33
C69: consumo totale | D69: =D68*D65 -> 240900
A74: Google stock | C74: A | D74: cash | E74: Google | F74: tasse | G74: guadagno lordo | J74: B | K74: cash | L74: Google | M74: tasse | N74: guadagno lordo | O74: minusvalenze da compensare
A75: 100 | D75: 100 | E75: 0 | F75: 0 | G75: 0 | H75: compro 1G | K75: 100 | L75: 0 | M75: 0 | N75: 0 | O75: 0 | P75: compro 1G
A76: 100 | D76: 0 | E76: 1 | F76: 0 | G76: 0 | K76: 0 | L76: 1 | M76: 0 | N76: 0 | O76: 0
A77: 100 | D77: 0 | E77: 1 | F77: 0 | G77: 0 | K77: 0 | L77: 1 | M77: 0 | N77: 0 | O77: 0
A78: 50 | D78: 0 | E78: 1 | F78: 0 | G78: 0 | K78: 0 | L78: 1 | M78: 0 | N78: 0 | O78: 0
A79: 50 | D79: 0 | E79: 1 | F79: 0 | G79: 0 | K79: 50 | L79: 0 | M79: 0 | N79: 0 | O79: =K75-K79 -> 50 | P79: vendo 1G
A80: 50 | D80: 0 | E80: 1 | F80: 0 | G80: 0 | K80: 0 | L80: 1 | M80: 0 | N80: 0 | O80: =O79 -> 50 | P80: compro 1G
A81: 50 | D81: 0 | E81: 1 | F81: 0 | G81: 0 | K81: 0 | L81: 1 | M81: 0 | N81: 0 | O81: =O80 -> 50
A82: 120 | D82: 0 | E82: 1 | F82: 0 | G82: 0 | K82: 0 | L82: 1 | M82: 0 | N82: 0 | O82: =O81 -> 50
A83: 120 | D83: 120 | E83: 0 | F83: =-0.26*G83 -> -5.2 | G83: =D83-D75 -> 20 | H83: vendo 1G | K83: 120 | L83: 0 | M83: 0 | N83: =K83-K79 -> 70 | O83: =O82 -> 50 | P83: vendo 1G
A84: 120 | D84: =D83+F83 -> 114.8 | E84: 0 | F84: 0 | G84: 0 | K84: 120 | L84: 0 | M84: =-0.26*N84 -> -5.2 | N84: =N83-O83 -> 20 | O84: 0 | P84: (compenso minusval.)
A85: 120 | D85: =D84+F84 -> 114.8 | E85: 0 | F85: 0 | G85: 0 | K85: =K84+M84 -> 114.8 | L85: 0 | M85: 0 | N85: 0 | O85: 0

Sheet Katane
B1: gp
A2: mu | B2: 2.5
A3: sigma^2 | B3: 0.7
A5: sample | B5: =ROUND(EXP($B$2 + $B$3^(0.5)* _xlfn.NORM.S.INV(RAND())),1) -> 18.5

Sheet Cash-flow
B3: Cash-flow Piantagione di Riso (1 contadino)
B5: voce | C5: valore | E5: voce | F5: valore
B6: area terreno [Kawa] | C6: 250 | E6: tassa terreno [$/Kawa] | F6: -0.25
B7: tasse terreno [$] | C7: =C6*F6 -> -62.5 | E7: prezzo semi [$/Ryoo] | F7: 1
B8: costo semi [$] | C8: =-F9*C6 -> -288 | E8: prezzo riso [$/Ryoo] | F8: 10
B9: utile [€] | C9: =F10*C6*F8 -> 6250 | E9: semi riso [$/Kawa] | F9: =0.12/0.375*3.6*F7 -> 1.152
E10: yield campo [Ryoo/Kawa] | F10: 2.5
B11: profitto ciclo | C11: =SUM(C7:C9) -> 5899.5
B12: mensile | C12: =C11/12 -> 491.625
B18: Cash-flow Sake
B20: voce | C20: valore | E20: voce | F20: valore | H20: Ryoo | I20: silver
B21: tempo produzione [mesi] | C21: 2 | E21: prezzo semi riso [$/Ryoo] | F21: 5 | H21: 150 | I21: =H21*8 -> 1200
B22: riso [Ryoo] | C22: 200 | E22: prezzo bottiglia [$/pezzo] | F22: 1 | H22: =H21*1.3 -> 195
B23: costo riso [$] | C23: =-C22*F21 -> -1000 | E23: Prezzo sake [$/bottiglia] | F23: 12
B24: affitto [$] | C24: =F26*C21 -> -300 | E24: [Ryoo/bottiglia] | F24: 2 | H24: bottiglie
B25: produzione [Ryoo] | C25: =C22*F27 -> 260 | E25: prezzo sake [$/Ryoo] | F25: 7 | H25: =H22/2 -> 97.5 | I25: =H25*16 -> 1560
B26: costo bottiglie [$] | C26: =-C25/F24*F22 -> -130 | E26: affitto [$/mese] | F26: -150 | I26: =H25*2 -> 195
B27: vendita bottiglie [$] | C27: =-C26 -> 130 | E27: rateo sake/riso | F27: 1.3
B28: utile sake [$] | C28: =C25*F25 -> 1820 | I28: =(I25-I21-I26) -> 165
B30: profitto ciclo | C30: =C24+C28+C23 -> 520
B34: Arbitraggio Mercantile
B36: voce | C36: valore | E36: voce | F36: valore
B37: capienza [unità] | C37: 100 | E37: tassa carovana [$/mese] | F37: -60
B38: numero di tratte mensili | C38: 20 | E38: prezzo di vendita [$/unità] | F38: 1.1
B39: volume mensile | C39: =C38*C37 -> 2000 | E39: prezzo di vendita [$/acquisto] | F39: 1
B40: spesa | C40: =-C39*F39 -> -2000
B41: spese tasse | C41: =F37 -> -60
B42: utile | C42: =C39*F38 -> 2200
B44: profitto mensile | C44: =SUM(C40:C42) -> 140
B48: Coltivazione Alghe
B50: voce | C50: valore | E50: voce | F50: valore
B51: superficie [Kawa] | C51: 100 | E51: prezzo alga essiccata [$/Ryoo] | F51: 0.3
B52: yield [Ryoo/Kawa/mese] | C52: 7 | E52: prezzo alga [$/Ryoo] | F52: 0.07
B53: personale | C53: =_xlfn.CEILING.MATH(C51/F54) -> 1 | E53: salario pert-time [$/mese] | F53: -100
B54: salari | C54: =C53*F53 -> -100 | E54: copertura [Kawa/persona] | F54: 100
B55: utile mensile [$] | C55: =C52*C51*F51 -> 210
B57: profitto mensile | C57: =SUM(C54:C55) -> 110
B61: Pirata
B63: voce | C63: valore | E63: voce | F63: valore
B64: superficie [Kawa] | C64: 140 | E64: Costo [$/Kawa] | F64: 5
B65: yield [Ryoo/Kawa/mese] | C65: =C64*F64 -> 700 | E65: Legno [$/Ryoo] | F65: 0.25
B66: legna
B70: Cameriere
B72: voce | C72: valore
B73: paga [Kawa/mese] | C73: 200
B74: vitto | C74: 0
B75: alloggio | C75: 0

Sheet Calendario
A1: IRL | B1: data in-game | C1: Anno | D1: Time-skip
A2: 45796 | B2: =A2-365.25 * (2025-2024) -47 -> 45383.75 | C2: =1532 -> 1532 | D2: =IF(WEEKDAY(A2,2)=7,"time-skip","")
A3: 45797 | B3: =B2+3 -> 45386.75 | C3: =C2+(DAY(B3)=1) * (MONTH(B3)=1) -> 1532 | D3: =IF(WEEKDAY(A3,2)=7,"time-skip","")
A4: 45798 | B4: =B2+7 -> 45390.75 | C4: =C3+(DAY(B4)=1) * (MONTH(B4)=1) -> 1532 | D4: =IF(WEEKDAY(A4,2)=7,"time-skip","")
A5: 45799 | B5: =B3+7 -> 45393.75 | C5: =C4+(DAY(B5)=1) * (MONTH(B5)=1) -> 1532 | D5: =IF(WEEKDAY(A5,2)=7,"time-skip","")
A6: 45800 | B6: =B4+7 -> 45397.75 | C6: =C5+(DAY(B6)=1) * (MONTH(B6)=1) -> 1532 | D6: =IF(WEEKDAY(A6,2)=7,"time-skip","")
A7: 45801 | B7: =B5+7 -> 45400.75 | C7: =C6+(DAY(B7)=1) * (MONTH(B7)=1) -> 1532 | D7: =IF(WEEKDAY(A7,2)=7,"time-skip","")
A8: 45802 | B8: =B6+7 -> 45404.75 | C8: =C7+(DAY(B8)=1) * (MONTH(B8)=1) -> 1532 | D8: =IF(WEEKDAY(A8,2)=7,"time-skip","") -> time-skip
A9: 45803 | B9: =B2+93-DAY(B2+93)+1 -> 45474.75 | C9: =C8+(DAY(B9)=1) * (MONTH(B9)=1) -> 1532 | D9: =IF(WEEKDAY(A9,2)=7,"time-skip","")
A10: 45804 | B10: =B9+3 -> 45477.75 | C10: =C9+(DAY(B10)=1) * (MONTH(B10)=1) -> 1532 | D10: =IF(WEEKDAY(A10,2)=7,"time-skip","")
A11: 45805 | B11: =B9+7 -> 45481.75 | C11: =C10+(DAY(B11)=1) * (MONTH(B11)=1) -> 1532 | D11: =IF(WEEKDAY(A11,2)=7,"time-skip","")
A12: 45806 | B12: =B10+7 -> 45484.75 | C12: =C11+(DAY(B12)=1) * (MONTH(B12)=1) -> 1532 | D12: =IF(WEEKDAY(A12,2)=7,"time-skip","")
A13: 45807 | B13: =B11+7 -> 45488.75 | C13: =C12+(DAY(B13)=1) * (MONTH(B13)=1) -> 1532 | D13: =IF(WEEKDAY(A13,2)=7,"time-skip","")
A14: 45808 | B14: =B12+7 -> 45491.75 | C14: =C13+(DAY(B14)=1) * (MONTH(B14)=1) -> 1532 | D14: =IF(WEEKDAY(A14,2)=7,"time-skip","")
A15: 45809 | B15: =B13+7 -> 45495.75 | C15: =C14+(DAY(B15)=1) * (MONTH(B15)=1) -> 1532 | D15: =IF(WEEKDAY(A15,2)=7,"time-skip","") -> time-skip
A16: 45810 | B16: =B9+93-DAY(B9+93)+1 -> 45566.75 | C16: =C15+(DAY(B16)=1) * (MONTH(B16)=1) -> 1532 | D16: =IF(WEEKDAY(A16,2)=7,"time-skip","")
A17: 45811 | B17: =B16+3 -> 45569.75 | C17: =C16+(DAY(B17)=1) * (MONTH(B17)=1) -> 1532 | D17: =IF(WEEKDAY(A17,2)=7,"time-skip","")
A18: 45812 | B18: =B16+7 -> 45573.75 | C18: =C17+(DAY(B18)=1) * (MONTH(B18)=1) -> 1532 | D18: =IF(WEEKDAY(A18,2)=7,"time-skip","")
A19: 45813 | B19: =B17+7 -> 45576.75 | C19: =C18+(DAY(B19)=1) * (MONTH(B19)=1) -> 1532 | D19: =IF(WEEKDAY(A19,2)=7,"time-skip","")
A20: 45814 | B20: =B18+7 -> 45580.75 | C20: =C19+(DAY(B20)=1) * (MONTH(B20)=1) -> 1532 | D20: =IF(WEEKDAY(A20,2)=7,"time-skip","")
A21: 45815 | B21: =B19+7 -> 45583.75 | C21: =C20+(DAY(B21)=1) * (MONTH(B21)=1) -> 1532 | D21: =IF(WEEKDAY(A21,2)=7,"time-skip","")
A22: 45816 | B22: =B20+7 -> 45587.75 | C22: =C21+(DAY(B22)=1) * (MONTH(B22)=1) -> 1532 | D22: =IF(WEEKDAY(A22,2)=7,"time-skip","") -> time-skip
A23: 45817 | B23: =B16+93-DAY(B16+93)+1 -> 45658.75 | C23: =C22+(DAY(B23)=1) * (MONTH(B23)=1) -> 1533 | D23: =IF(WEEKDAY(A23,2)=7,"time-skip","")
A24: 45818 | B24: =B23+3 -> 45661.75 | C24: =C23+(DAY(B24)=1) * (MONTH(B24)=1) -> 1533 | D24: =IF(WEEKDAY(A24,2)=7,"time-skip","")
A25: 45819 | B25: =B23+7 -> 45665.75 | C25: =C24+(DAY(B25)=1) * (MONTH(B25)=1) -> 1533 | D25: =IF(WEEKDAY(A25,2)=7,"time-skip","")
A26: 45820 | B26: =B24+7 -> 45668.75 | C26: =C25+(DAY(B26)=1) * (MONTH(B26)=1) -> 1533 | D26: =IF(WEEKDAY(A26,2)=7,"time-skip","")
A27: 45821 | B27: =B25+7 -> 45672.75 | C27: =C26+(DAY(B27)=1) * (MONTH(B27)=1) -> 1533 | D27: =IF(WEEKDAY(A27,2)=7,"time-skip","")
A28: 45822 | B28: =B26+7 -> 45675.75 | C28: =C27+(DAY(B28)=1) * (MONTH(B28)=1) -> 1533 | D28: =IF(WEEKDAY(A28,2)=7,"time-skip","")
A29: 45823 | B29: =B27+7 -> 45679.75 | C29: =C28+(DAY(B29)=1) * (MONTH(B29)=1) -> 1533 | D29: =IF(WEEKDAY(A29,2)=7,"time-skip","") -> time-skip
A30: 45824 | B30: =B23+93-DAY(B23+93)+1 -> 45748.75 | C30: =C29+(DAY(B30)=1) * (MONTH(B30)=1) -> 1533 | D30: =IF(WEEKDAY(A30,2)=7,"time-skip","")
A31: 45825 | B31: =B30+3 -> 45751.75 | C31: =C30+(DAY(B31)=1) * (MONTH(B31)=1) -> 1533 | D31: =IF(WEEKDAY(A31,2)=7,"time-skip","")
A32: 45826 | B32: =B30+7 -> 45755.75 | C32: =C31+(DAY(B32)=1) * (MONTH(B32)=1) -> 1533 | D32: =IF(WEEKDAY(A32,2)=7,"time-skip","")
A33: 45827 | B33: =B31+7 -> 45758.75 | C33: =C32+(DAY(B33)=1) * (MONTH(B33)=1) -> 1533 | D33: =IF(WEEKDAY(A33,2)=7,"time-skip","")
A34: 45828 | B34: =B32+7 -> 45762.75 | C34: =C33+(DAY(B34)=1) * (MONTH(B34)=1) -> 1533 | D34: =IF(WEEKDAY(A34,2)=7,"time-skip","")
A35: 45829 | B35: =B33+7 -> 45765.75 | C35: =C34+(DAY(B35)=1) * (MONTH(B35)=1) -> 1533 | D35: =IF(WEEKDAY(A35,2)=7,"time-skip","")
A36: 45830 | B36: =B34+7 -> 45769.75 | C36: =C35+(DAY(B36)=1) * (MONTH(B36)=1) -> 1533 | D36: =IF(WEEKDAY(A36,2)=7,"time-skip","") -> time-skip
A37: 45831 | B37: =B30+93-DAY(B30+93)+1 -> 45839.75 | C37: =C36+(DAY(B37)=1) * (MONTH(B37)=1) -> 1533 | D37: =IF(WEEKDAY(A37,2)=7,"time-skip","")
A38: 45832 | B38: =B37+3 -> 45842.75 | C38: =C37+(DAY(B38)=1) * (MONTH(B38)=1) -> 1533 | D38: =IF(WEEKDAY(A38,2)=7,"time-skip","")
A39: 45833 | B39: =B37+7 -> 45846.75 | C39: =C38+(DAY(B39)=1) * (MONTH(B39)=1) -> 1533 | D39: =IF(WEEKDAY(A39,2)=7,"time-skip","")
A40: 45834 | B40: =B38+7 -> 45849.75 | C40: =C39+(DAY(B40)=1) * (MONTH(B40)=1) -> 1533 | D40: =IF(WEEKDAY(A40,2)=7,"time-skip","")
A41: 45835 | B41: =B39+7 -> 45853.75 | C41: =C40+(DAY(B41)=1) * (MONTH(B41)=1) -> 1533 | D41: =IF(WEEKDAY(A41,2)=7,"time-skip","")
A42: 45836 | B42: =B40+7 -> 45856.75 | C42: =C41+(DAY(B42)=1) * (MONTH(B42)=1) -> 1533 | D42: =IF(WEEKDAY(A42,2)=7,"time-skip","")
A43: 45837 | B43: =B41+7 -> 45860.75 | C43: =C42+(DAY(B43)=1) * (MONTH(B43)=1) -> 1533 | D43: =IF(WEEKDAY(A43,2)=7,"time-skip","") -> time-skip
A44: 45838 | B44: =B37+93-DAY(B37+93)+1 -> 45931.75 | C44: =C43+(DAY(B44)=1) * (MONTH(B44)=1) -> 1533 | D44: =IF(WEEKDAY(A44,2)=7,"time-skip","")
A45: 45839 | B45: =B44+3 -> 45934.75 | C45: =C44+(DAY(B45)=1) * (MONTH(B45)=1) -> 1533 | D45: =IF(WEEKDAY(A45,2)=7,"time-skip","")
A46: 45840 | B46: =B44+7 -> 45938.75 | C46: =C45+(DAY(B46)=1) * (MONTH(B46)=1) -> 1533 | D46: =IF(WEEKDAY(A46,2)=7,"time-skip","")
A47: 45841 | B47: =B45+7 -> 45941.75 | C47: =C46+(DAY(B47)=1) * (MONTH(B47)=1) -> 1533 | D47: =IF(WEEKDAY(A47,2)=7,"time-skip","")
A48: 45842 | B48: =B46+7 -> 45945.75 | C48: =C47+(DAY(B48)=1) * (MONTH(B48)=1) -> 1533 | D48: =IF(WEEKDAY(A48,2)=7,"time-skip","")
A49: 45843 | B49: =B47+7 -> 45948.75 | C49: =C48+(DAY(B49)=1) * (MONTH(B49)=1) -> 1533 | D49: =IF(WEEKDAY(A49,2)=7,"time-skip","")
A50: 45844 | B50: =B48+7 -> 45952.75 | C50: =C49+(DAY(B50)=1) * (MONTH(B50)=1) -> 1533 | D50: =IF(WEEKDAY(A50,2)=7,"time-skip","") -> time-skip
A51: 45845 | B51: =B44+93-DAY(B44+93)+1 -> 46023.75 | C51: =C50+(DAY(B51)=1) * (MONTH(B51)=1) -> 1534 | D51: =IF(WEEKDAY(A51,2)=7,"time-skip","")
A52: 45846 | B52: =B51+3 -> 46026.75 | C52: =C51+(DAY(B52)=1) * (MONTH(B52)=1) -> 1534 | D52: =IF(WEEKDAY(A52,2)=7,"time-skip","")
A53: 45847 | B53: =B51+7 -> 46030.75 | C53: =C52+(DAY(B53)=1) * (MONTH(B53)=1) -> 1534 | D53: =IF(WEEKDAY(A53,2)=7,"time-skip","")
A54: 45848 | B54: =B52+7 -> 46033.75 | C54: =C53+(DAY(B54)=1) * (MONTH(B54)=1) -> 1534 | D54: =IF(WEEKDAY(A54,2)=7,"time-skip","")
A55: 45849 | B55: =B53+7 -> 46037.75 | C55: =C54+(DAY(B55)=1) * (MONTH(B55)=1) -> 1534 | D55: =IF(WEEKDAY(A55,2)=7,"time-skip","")
A56: 45850 | B56: =B54+7 -> 46040.75 | C56: =C55+(DAY(B56)=1) * (MONTH(B56)=1) -> 1534 | D56: =IF(WEEKDAY(A56,2)=7,"time-skip","")
A57: 45851 | B57: =B55+7 -> 46044.75 | C57: =C56+(DAY(B57)=1) * (MONTH(B57)=1) -> 1534 | D57: =IF(WEEKDAY(A57,2)=7,"time-skip","") -> time-skip
A58: 45852 | B58: =B51+93-DAY(B51+93)+1 -> 46113.75 | C58: =C57+(DAY(B58)=1) * (MONTH(B58)=1) -> 1534 | D58: =IF(WEEKDAY(A58,2)=7,"time-skip","")
A59: 45853 | B59: =B58+3 -> 46116.75 | C59: =C58+(DAY(B59)=1) * (MONTH(B59)=1) -> 1534 | D59: =IF(WEEKDAY(A59,2)=7,"time-skip","")
A60: 45854 | B60: =B58+7 -> 46120.75 | C60: =C59+(DAY(B60)=1) * (MONTH(B60)=1) -> 1534 | D60: =IF(WEEKDAY(A60,2)=7,"time-skip","")
A61: 45855 | B61: =B59+7 -> 46123.75 | C61: =C60+(DAY(B61)=1) * (MONTH(B61)=1) -> 1534 | D61: =IF(WEEKDAY(A61,2)=7,"time-skip","")
A62: 45856 | B62: =B60+7 -> 46127.75 | C62: =C61+(DAY(B62)=1) * (MONTH(B62)=1) -> 1534 | D62: =IF(WEEKDAY(A62,2)=7,"time-skip","")
A63: 45857 | B63: =B61+7 -> 46130.75 | C63: =C62+(DAY(B63)=1) * (MONTH(B63)=1) -> 1534 | D63: =IF(WEEKDAY(A63,2)=7,"time-skip","")
A64: 45858 | B64: =B62+7 -> 46134.75 | C64: =C63+(DAY(B64)=1) * (MONTH(B64)=1) -> 1534 | D64: =IF(WEEKDAY(A64,2)=7,"time-skip","") -> time-skip
A65: 45859 | B65: =B58+93-DAY(B58+93)+1 -> 46204.75 | C65: =C64+(DAY(B65)=1) * (MONTH(B65)=1) -> 1534 | D65: =IF(WEEKDAY(A65,2)=7,"time-skip","")
A66: 45860 | B66: =B65+3 -> 46207.75 | C66: =C65+(DAY(B66)=1) * (MONTH(B66)=1) -> 1534 | D66: =IF(WEEKDAY(A66,2)=7,"time-skip","")
A67: 45861 | B67: =B65+7 -> 46211.75 | C67: =C66+(DAY(B67)=1) * (MONTH(B67)=1) -> 1534 | D67: =IF(WEEKDAY(A67,2)=7,"time-skip","")
A68: 45862 | B68: =B66+7 -> 46214.75 | C68: =C67+(DAY(B68)=1) * (MONTH(B68)=1) -> 1534 | D68: =IF(WEEKDAY(A68,2)=7,"time-skip","")
A69: 45863 | B69: =B67+7 -> 46218.75 | C69: =C68+(DAY(B69)=1) * (MONTH(B69)=1) -> 1534 | D69: =IF(WEEKDAY(A69,2)=7,"time-skip","")
A70: 45864 | B70: =B68+7 -> 46221.75 | C70: =C69+(DAY(B70)=1) * (MONTH(B70)=1) -> 1534 | D70: =IF(WEEKDAY(A70,2)=7,"time-skip","")
A71: 45865 | B71: =B69+7 -> 46225.75 | C71: =C70+(DAY(B71)=1) * (MONTH(B71)=1) -> 1534 | D71: =IF(WEEKDAY(A71,2)=7,"time-skip","") -> time-skip
A72: 45866 | B72: =B65+93-DAY(B65+93)+1 -> 46296.75 | C72: =C71+(DAY(B72)=1) * (MONTH(B72)=1) -> 1534 | D72: =IF(WEEKDAY(A72,2)=7,"time-skip","")
A73: 45867 | B73: =B72+3 -> 46299.75 | C73: =C72+(DAY(B73)=1) * (MONTH(B73)=1) -> 1534 | D73: =IF(WEEKDAY(A73,2)=7,"time-skip","")
A74: 45868 | B74: =B72+7 -> 46303.75 | C74: =C73+(DAY(B74)=1) * (MONTH(B74)=1) -> 1534 | D74: =IF(WEEKDAY(A74,2)=7,"time-skip","")
A75: 45869 | B75: =B73+7 -> 46306.75 | C75: =C74+(DAY(B75)=1) * (MONTH(B75)=1) -> 1534 | D75: =IF(WEEKDAY(A75,2)=7,"time-skip","")
A76: 45870 | B76: =B74+7 -> 46310.75 | C76: =C75+(DAY(B76)=1) * (MONTH(B76)=1) -> 1534 | D76: =IF(WEEKDAY(A76,2)=7,"time-skip","")
A77: 45871 | B77: =B75+7 -> 46313.75 | C77: =C76+(DAY(B77)=1) * (MONTH(B77)=1) -> 1534 | D77: =IF(WEEKDAY(A77,2)=7,"time-skip","")
A78: 45872 | B78: =B76+7 -> 46317.75 | C78: =C77+(DAY(B78)=1) * (MONTH(B78)=1) -> 1534 | D78: =IF(WEEKDAY(A78,2)=7,"time-skip","") -> time-skip
A79: 45873 | B79: =B72+93-DAY(B72+93)+1 -> 46388.75 | C79: =C78+(DAY(B79)=1) * (MONTH(B79)=1) -> 1535 | D79: =IF(WEEKDAY(A79,2)=7,"time-skip","")
A80: 45874 | B80: =B79+3 -> 46391.75 | C80: =C79+(DAY(B80)=1) * (MONTH(B80)=1) -> 1535 | D80: =IF(WEEKDAY(A80,2)=7,"time-skip","")
A81: 45875 | B81: =B79+7 -> 46395.75 | C81: =C80+(DAY(B81)=1) * (MONTH(B81)=1) -> 1535 | D81: =IF(WEEKDAY(A81,2)=7,"time-skip","")
A82: 45876 | B82: =B80+7 -> 46398.75 | C82: =C81+(DAY(B82)=1) * (MONTH(B82)=1) -> 1535 | D82: =IF(WEEKDAY(A82,2)=7,"time-skip","")
A83: 45877 | B83: =B81+7 -> 46402.75 | C83: =C82+(DAY(B83)=1) * (MONTH(B83)=1) -> 1535 | D83: =IF(WEEKDAY(A83,2)=7,"time-skip","")
A84: 45878 | B84: =B82+7 -> 46405.75 | C84: =C83+(DAY(B84)=1) * (MONTH(B84)=1) -> 1535 | D84: =IF(WEEKDAY(A84,2)=7,"time-skip","")
A85: 45879 | B85: =B83+7 -> 46409.75 | C85: =C84+(DAY(B85)=1) * (MONTH(B85)=1) -> 1535 | D85: =IF(WEEKDAY(A85,2)=7,"time-skip","") -> time-skip
A86: 45880 | B86: =B79+93-DAY(B79+93)+1 -> 46478.75 | C86: =C85+(DAY(B86)=1) * (MONTH(B86)=1) -> 1535 | D86: =IF(WEEKDAY(A86,2)=7,"time-skip","")
A87: 45881 | B87: =B86+3 -> 46481.75 | C87: =C86+(DAY(B87)=1) * (MONTH(B87)=1) -> 1535 | D87: =IF(WEEKDAY(A87,2)=7,"time-skip","")
A88: 45882 | B88: =B86+7 -> 46485.75 | C88: =C87+(DAY(B88)=1) * (MONTH(B88)=1) -> 1535 | D88: =IF(WEEKDAY(A88,2)=7,"time-skip","")
A89: 45883 | B89: =B87+7 -> 46488.75 | C89: =C88+(DAY(B89)=1) * (MONTH(B89)=1) -> 1535 | D89: =IF(WEEKDAY(A89,2)=7,"time-skip","")
A90: 45884 | B90: =B88+7 -> 46492.75 | C90: =C89+(DAY(B90)=1) * (MONTH(B90)=1) -> 1535 | D90: =IF(WEEKDAY(A90,2)=7,"time-skip","")
A91: 45885 | B91: =B89+7 -> 46495.75 | C91: =C90+(DAY(B91)=1) * (MONTH(B91)=1) -> 1535 | D91: =IF(WEEKDAY(A91,2)=7,"time-skip","")
A92: 45886 | B92: =B90+7 -> 46499.75 | C92: =C91+(DAY(B92)=1) * (MONTH(B92)=1) -> 1535 | D92: =IF(WEEKDAY(A92,2)=7,"time-skip","") -> time-skip
A93: 45887 | B93: =B86+93-DAY(B86+93)+1 -> 46569.75 | C93: =C92+(DAY(B93)=1) * (MONTH(B93)=1) -> 1535 | D93: =IF(WEEKDAY(A93,2)=7,"time-skip","")
A94: 45888 | B94: =B93+3 -> 46572.75 | C94: =C93+(DAY(B94)=1) * (MONTH(B94)=1) -> 1535 | D94: =IF(WEEKDAY(A94,2)=7,"time-skip","")
A95: 45889 | B95: =B93+7 -> 46576.75 | C95: =C94+(DAY(B95)=1) * (MONTH(B95)=1) -> 1535 | D95: =IF(WEEKDAY(A95,2)=7,"time-skip","")
A96: 45890 | B96: =B94+7 -> 46579.75 | C96: =C95+(DAY(B96)=1) * (MONTH(B96)=1) -> 1535 | D96: =IF(WEEKDAY(A96,2)=7,"time-skip","")
A97: 45891 | B97: =B95+7 -> 46583.75 | C97: =C96+(DAY(B97)=1) * (MONTH(B97)=1) -> 1535 | D97: =IF(WEEKDAY(A97,2)=7,"time-skip","")
A98: 45892 | B98: =B96+7 -> 46586.75 | C98: =C97+(DAY(B98)=1) * (MONTH(B98)=1) -> 1535 | D98: =IF(WEEKDAY(A98,2)=7,"time-skip","")
A99: 45893 | B99: =B97+7 -> 46590.75 | C99: =C98+(DAY(B99)=1) * (MONTH(B99)=1) -> 1535 | D99: =IF(WEEKDAY(A99,2)=7,"time-skip","") -> time-skip
A100: 45894 | B100: =B93+93-DAY(B93+93)+1 -> 46661.75 | C100: =C99+(DAY(B100)=1) * (MONTH(B100)=1) -> 1535 | D100: =IF(WEEKDAY(A100,2)=7,"time-skip","")
...

Sheet yield
B2: Guadagni annui a persona
C4: superficie [Kawa] | D4: primavera [mesi] | E4: estate [mesi] | F4: autunno [mesi] | G4: produzione [Ryoo/Kawa] | H4: Produzione [Ryoo/anno] | I4: Prezzo [$/Ryoo] | J4: Guadagno [ $/mese]
B5: patate | C5: 500 | D5: 3 | E5: 3 | G5: 2.5 | H5: =G5*C5 -> 1250 | I5: 4 | J5: =I5*H5/SUM(D5:F5) -> 833.33333 | L5: =J5/C5 -> 1.6666667
B6: riso | C6: 500 | D6: 3 | E6: 3 | G6: 5 | H6: =G6*C6 -> 2500 | I6: 10 | J6: =I6*H6/SUM(D6:F6) -> 4166.6667 | L6: =J6/C6 -> 8.3333333
B7: fagioli | C7: 200 | D7: 3 | G7: 1.5 | H7: =G7*C7 -> 300 | I7: 12 | J7: =I7*H7/SUM(D7:F7) -> 1200 | L7: =J7/C7 -> 6
B8: foglie di tè | C8: 200 | D8: 3 | E8: 3 | G8: 1 | H8: =G8*C8 -> 200 | I8: 4.5 | J8: =I8*H8/SUM(D8:F8) -> 150 | L8: =J8/C8 -> 0.75
B9: alghe | C9: 200 | D9: 3 | E9: 3 | G9: 10 | H9: =G9*C9 -> 2000 | I9: 0.07 | J9: =I9*H9/SUM(D9:F9) -> 23.333333 | L9: =J9/C9 -> 0.11666667
B10: bambù | C10: 100 | D10: 3 | F10: 3 | G10: 300 | H10: =G10*C10 -> 30000 | I10: 0.04 | J10: =I10*H10/SUM(D10:F10) -> 200 | L10: =J10/C10 -> 2
B11: legna | C11: 100 | D11: 3 | E11: 3 | F11: 3 | G11: 150 | H11: =G11*C11 -> 15000 | I11: 0.25 | J11: =I11*H11/SUM(D11:F11) -> 416.66667 | L11: =J11/C11 -> 4.1666667
B12: cocco | C12: -- | D12: -- | E12: -- | F12: -- | G12: -- | H12: 100 | I12: 12 | J12: =I12*H12/12 -> 100
B13: pesca | C13: -- | D13: -- | E13: -- | F13: -- | G13: -- | H13: 300 | I13: 10 | J13: =I13*H13/12 -> 250
C19: 189 | D19: €/m^2 | E19: 1 | F19: ha | G19: 500 | H19: Kawa | I19: 10 | J19: q/ha
C20: =C19/3*3.6 -> 226.8 | D20: $/kawa | E20: =E19*10000/3.6 -> 2777.7778 | F20: Kawa | G20: =G19*3.6/10000 -> 0.18 | H20: ha | I20: =I19*100/0.375/10000*3.6 -> 0.96 | J20: Ryoo/Kawa
